[{"arguments":["clang","-Wno-documentation-unknown-command","-Wno-unknown-warning-option","-Wno-unknown-pragmas","-nostdinc","-nostdinc++","-g","-Wall","-Wextra","-Wextra","-fexceptions","-mthreads","-fsyntax-only","-m64","--target=x86_64-w64-mingw32","-std=gnu++17","-DUNICODE","-D_UNICODE","-DWIN32","-DMINGW_HAS_SECURE_API","-DQT_QML_DEBUG","-DQT_WIDGETS_LIB","-DQT_MULTIMEDIA_LIB","-DQT_GUI_LIB","-DQT_NETWORK_LIB","-DQT_CORE_LIB","-DQT_NEEDS_QMAIN","-DQ_CREATOR_RUN","-DQT_ANNOTATE_FUNCTION(x)=__attribute__((annotate(#x)))","-IC:\\Qt\\Tools\\QtCreator\\share\\qtcreator\\cplusplus\\wrappedMingwHeaders","-IC:\\Qt\\Tools\\QtCreator\\share\\qtcreator\\cplusplus\\wrappedQtHeaders","-IC:\\Qt\\Tools\\QtCreator\\share\\qtcreator\\cplusplus\\wrappedQtHeaders\\QtCore","-ID:\\Qt\\Project\\EntryPage","-IC:\\Qt\\6.6.3\\mingw_64\\include","-IC:\\Qt\\6.6.3\\mingw_64\\include\\QtWidgets","-IC:\\Qt\\6.6.3\\mingw_64\\include\\QtMultimedia","-IC:\\Qt\\6.6.3\\mingw_64\\include\\QtGui","-IC:\\Qt\\6.6.3\\mingw_64\\include\\QtNetwork","-IC:\\Qt\\6.6.3\\mingw_64\\include\\QtCore","-ID:\\Qt\\Project\\EntryPage\\build\\Desktop_Qt_6_6_3_MinGW_64_bit-Debug\\debug","-ID:\\Qt\\Project\\EntryPage\\build\\Desktop_Qt_6_6_3_MinGW_64_bit-Debug","-IC:\\Qt\\6.6.3\\mingw_64\\mkspecs\\win32-g++","-isystem","C:\\Qt\\Tools\\mingw1120_64\\lib\\gcc\\x86_64-w64-mingw32\\11.2.0\\include\\c++","-isystem","C:\\Qt\\Tools\\mingw1120_64\\lib\\gcc\\x86_64-w64-mingw32\\11.2.0\\include\\c++\\x86_64-w64-mingw32","-isystem","C:\\Qt\\Tools\\mingw1120_64\\lib\\gcc\\x86_64-w64-mingw32\\11.2.0\\include\\c++\\backward","-isystem","C:\\Qt\\Tools\\QtCreator\\bin\\clang\\lib\\clang\\17\\include","-isystem","C:\\Qt\\Tools\\mingw1120_64\\x86_64-w64-mingw32\\include","-fmessage-length=0","-fdiagnostics-show-note-include-stack","-fretain-comments-from-system-headers","-fmacro-backtrace-limit=0","-ferror-limit=1000","-x","c++","D:\\Qt\\Project\\EntryPage\\arms.cpp"],"directory":"D:/Qt/Project/EntryPage/build/Desktop_Qt_6_6_3_MinGW_64_bit-Debug/.qtc_clangd","file":"D:/Qt/Project/EntryPage/arms.cpp"},{"arguments":["clang","-Wno-documentation-unknown-command","-Wno-unknown-warning-option","-Wno-unknown-pragmas","-nostdinc","-nostdinc++","-g","-Wall","-Wextra","-Wextra","-fexceptions","-mthreads","-fsyntax-only","-m64","--target=x86_64-w64-mingw32","-std=gnu++17","-DUNICODE","-D_UNICODE","-DWIN32","-DMINGW_HAS_SECURE_API","-DQT_QML_DEBUG","-DQT_WIDGETS_LIB","-DQT_MULTIMEDIA_LIB","-DQT_GUI_LIB","-DQT_NETWORK_LIB","-DQT_CORE_LIB","-DQT_NEEDS_QMAIN","-DQ_CREATOR_RUN","-DQT_ANNOTATE_FUNCTION(x)=__attribute__((annotate(#x)))","-IC:\\Qt\\Tools\\QtCreator\\share\\qtcreator\\cplusplus\\wrappedMingwHeaders","-IC:\\Qt\\Tools\\QtCreator\\share\\qtcreator\\cplusplus\\wrappedQtHeaders","-IC:\\Qt\\Tools\\QtCreator\\share\\qtcreator\\cplusplus\\wrappedQtHeaders\\QtCore","-ID:\\Qt\\Project\\EntryPage","-IC:\\Qt\\6.6.3\\mingw_64\\include","-IC:\\Qt\\6.6.3\\mingw_64\\include\\QtWidgets","-IC:\\Qt\\6.6.3\\mingw_64\\include\\QtMultimedia","-IC:\\Qt\\6.6.3\\mingw_64\\include\\QtGui","-IC:\\Qt\\6.6.3\\mingw_64\\include\\QtNetwork","-IC:\\Qt\\6.6.3\\mingw_64\\include\\QtCore","-ID:\\Qt\\Project\\EntryPage\\build\\Desktop_Qt_6_6_3_MinGW_64_bit-Debug\\debug","-ID:\\Qt\\Project\\EntryPage\\build\\Desktop_Qt_6_6_3_MinGW_64_bit-Debug","-IC:\\Qt\\6.6.3\\mingw_64\\mkspecs\\win32-g++","-isystem","C:\\Qt\\Tools\\mingw1120_64\\lib\\gcc\\x86_64-w64-mingw32\\11.2.0\\include\\c++","-isystem","C:\\Qt\\Tools\\mingw1120_64\\lib\\gcc\\x86_64-w64-mingw32\\11.2.0\\include\\c++\\x86_64-w64-mingw32","-isystem","C:\\Qt\\Tools\\mingw1120_64\\lib\\gcc\\x86_64-w64-mingw32\\11.2.0\\include\\c++\\backward","-isystem","C:\\Qt\\Tools\\QtCreator\\bin\\clang\\lib\\clang\\17\\include","-isystem","C:\\Qt\\Tools\\mingw1120_64\\x86_64-w64-mingw32\\include","-fmessage-length=0","-fdiagnostics-show-note-include-stack","-fretain-comments-from-system-headers","-fmacro-backtrace-limit=0","-ferror-limit=1000","-x","c++","D:\\Qt\\Project\\EntryPage\\dialoggameai.cpp"],"directory":"D:/Qt/Project/EntryPage/build/Desktop_Qt_6_6_3_MinGW_64_bit-Debug/.qtc_clangd","file":"D:/Qt/Project/EntryPage/dialoggameai.cpp"},{"arguments":["clang","-Wno-documentation-unknown-command","-Wno-unknown-warning-option","-Wno-unknown-pragmas","-nostdinc","-nostdinc++","-g","-Wall","-Wextra","-Wextra","-fexceptions","-mthreads","-fsyntax-only","-m64","--target=x86_64-w64-mingw32","-std=gnu++17","-DUNICODE","-D_UNICODE","-DWIN32","-DMINGW_HAS_SECURE_API","-DQT_QML_DEBUG","-DQT_WIDGETS_LIB","-DQT_MULTIMEDIA_LIB","-DQT_GUI_LIB","-DQT_NETWORK_LIB","-DQT_CORE_LIB","-DQT_NEEDS_QMAIN","-DQ_CREATOR_RUN","-DQT_ANNOTATE_FUNCTION(x)=__attribute__((annotate(#x)))","-IC:\\Qt\\Tools\\QtCreator\\share\\qtcreator\\cplusplus\\wrappedMingwHeaders","-IC:\\Qt\\Tools\\QtCreator\\share\\qtcreator\\cplusplus\\wrappedQtHeaders","-IC:\\Qt\\Tools\\QtCreator\\share\\qtcreator\\cplusplus\\wrappedQtHeaders\\QtCore","-ID:\\Qt\\Project\\EntryPage","-IC:\\Qt\\6.6.3\\mingw_64\\include","-IC:\\Qt\\6.6.3\\mingw_64\\include\\QtWidgets","-IC:\\Qt\\6.6.3\\mingw_64\\include\\QtMultimedia","-IC:\\Qt\\6.6.3\\mingw_64\\include\\QtGui","-IC:\\Qt\\6.6.3\\mingw_64\\include\\QtNetwork","-IC:\\Qt\\6.6.3\\mingw_64\\include\\QtCore","-ID:\\Qt\\Project\\EntryPage\\build\\Desktop_Qt_6_6_3_MinGW_64_bit-Debug\\debug","-ID:\\Qt\\Project\\EntryPage\\build\\Desktop_Qt_6_6_3_MinGW_64_bit-Debug","-IC:\\Qt\\6.6.3\\mingw_64\\mkspecs\\win32-g++","-isystem","C:\\Qt\\Tools\\mingw1120_64\\lib\\gcc\\x86_64-w64-mingw32\\11.2.0\\include\\c++","-isystem","C:\\Qt\\Tools\\mingw1120_64\\lib\\gcc\\x86_64-w64-mingw32\\11.2.0\\include\\c++\\x86_64-w64-mingw32","-isystem","C:\\Qt\\Tools\\mingw1120_64\\lib\\gcc\\x86_64-w64-mingw32\\11.2.0\\include\\c++\\backward","-isystem","C:\\Qt\\Tools\\QtCreator\\bin\\clang\\lib\\clang\\17\\include","-isystem","C:\\Qt\\Tools\\mingw1120_64\\x86_64-w64-mingw32\\include","-fmessage-length=0","-fdiagnostics-show-note-include-stack","-fretain-comments-from-system-headers","-fmacro-backtrace-limit=0","-ferror-limit=1000","-x","c++","D:\\Qt\\Project\\EntryPage\\dialoggetarm.cpp"],"directory":"D:/Qt/Project/EntryPage/build/Desktop_Qt_6_6_3_MinGW_64_bit-Debug/.qtc_clangd","file":"D:/Qt/Project/EntryPage/dialoggetarm.cpp"},{"arguments":["clang","-Wno-documentation-unknown-command","-Wno-unknown-warning-option","-Wno-unknown-pragmas","-nostdinc","-nostdinc++","-g","-Wall","-Wextra","-Wextra","-fexceptions","-mthreads","-fsyntax-only","-m64","--target=x86_64-w64-mingw32","-std=gnu++17","-DUNICODE","-D_UNICODE","-DWIN32","-DMINGW_HAS_SECURE_API","-DQT_QML_DEBUG","-DQT_WIDGETS_LIB","-DQT_MULTIMEDIA_LIB","-DQT_GUI_LIB","-DQT_NETWORK_LIB","-DQT_CORE_LIB","-DQT_NEEDS_QMAIN","-DQ_CREATOR_RUN","-DQT_ANNOTATE_FUNCTION(x)=__attribute__((annotate(#x)))","-IC:\\Qt\\Tools\\QtCreator\\share\\qtcreator\\cplusplus\\wrappedMingwHeaders","-IC:\\Qt\\Tools\\QtCreator\\share\\qtcreator\\cplusplus\\wrappedQtHeaders","-IC:\\Qt\\Tools\\QtCreator\\share\\qtcreator\\cplusplus\\wrappedQtHeaders\\QtCore","-ID:\\Qt\\Project\\EntryPage","-IC:\\Qt\\6.6.3\\mingw_64\\include","-IC:\\Qt\\6.6.3\\mingw_64\\include\\QtWidgets","-IC:\\Qt\\6.6.3\\mingw_64\\include\\QtMultimedia","-IC:\\Qt\\6.6.3\\mingw_64\\include\\QtGui","-IC:\\Qt\\6.6.3\\mingw_64\\include\\QtNetwork","-IC:\\Qt\\6.6.3\\mingw_64\\include\\QtCore","-ID:\\Qt\\Project\\EntryPage\\build\\Desktop_Qt_6_6_3_MinGW_64_bit-Debug\\debug","-ID:\\Qt\\Project\\EntryPage\\build\\Desktop_Qt_6_6_3_MinGW_64_bit-Debug","-IC:\\Qt\\6.6.3\\mingw_64\\mkspecs\\win32-g++","-isystem","C:\\Qt\\Tools\\mingw1120_64\\lib\\gcc\\x86_64-w64-mingw32\\11.2.0\\include\\c++","-isystem","C:\\Qt\\Tools\\mingw1120_64\\lib\\gcc\\x86_64-w64-mingw32\\11.2.0\\include\\c++\\x86_64-w64-mingw32","-isystem","C:\\Qt\\Tools\\mingw1120_64\\lib\\gcc\\x86_64-w64-mingw32\\11.2.0\\include\\c++\\backward","-isystem","C:\\Qt\\Tools\\QtCreator\\bin\\clang\\lib\\clang\\17\\include","-isystem","C:\\Qt\\Tools\\mingw1120_64\\x86_64-w64-mingw32\\include","-fmessage-length=0","-fdiagnostics-show-note-include-stack","-fretain-comments-from-system-headers","-fmacro-backtrace-limit=0","-ferror-limit=1000","-x","c++","D:\\Qt\\Project\\EntryPage\\dialogpage1.cpp"],"directory":"D:/Qt/Project/EntryPage/build/Desktop_Qt_6_6_3_MinGW_64_bit-Debug/.qtc_clangd","file":"D:/Qt/Project/EntryPage/dialogpage1.cpp"},{"arguments":["clang","-Wno-documentation-unknown-command","-Wno-unknown-warning-option","-Wno-unknown-pragmas","-nostdinc","-nostdinc++","-g","-Wall","-Wextra","-Wextra","-fexceptions","-mthreads","-fsyntax-only","-m64","--target=x86_64-w64-mingw32","-std=gnu++17","-DUNICODE","-D_UNICODE","-DWIN32","-DMINGW_HAS_SECURE_API","-DQT_QML_DEBUG","-DQT_WIDGETS_LIB","-DQT_MULTIMEDIA_LIB","-DQT_GUI_LIB","-DQT_NETWORK_LIB","-DQT_CORE_LIB","-DQT_NEEDS_QMAIN","-DQ_CREATOR_RUN","-DQT_ANNOTATE_FUNCTION(x)=__attribute__((annotate(#x)))","-IC:\\Qt\\Tools\\QtCreator\\share\\qtcreator\\cplusplus\\wrappedMingwHeaders","-IC:\\Qt\\Tools\\QtCreator\\share\\qtcreator\\cplusplus\\wrappedQtHeaders","-IC:\\Qt\\Tools\\QtCreator\\share\\qtcreator\\cplusplus\\wrappedQtHeaders\\QtCore","-ID:\\Qt\\Project\\EntryPage","-IC:\\Qt\\6.6.3\\mingw_64\\include","-IC:\\Qt\\6.6.3\\mingw_64\\include\\QtWidgets","-IC:\\Qt\\6.6.3\\mingw_64\\include\\QtMultimedia","-IC:\\Qt\\6.6.3\\mingw_64\\include\\QtGui","-IC:\\Qt\\6.6.3\\mingw_64\\include\\QtNetwork","-IC:\\Qt\\6.6.3\\mingw_64\\include\\QtCore","-ID:\\Qt\\Project\\EntryPage\\build\\Desktop_Qt_6_6_3_MinGW_64_bit-Debug\\debug","-ID:\\Qt\\Project\\EntryPage\\build\\Desktop_Qt_6_6_3_MinGW_64_bit-Debug","-IC:\\Qt\\6.6.3\\mingw_64\\mkspecs\\win32-g++","-isystem","C:\\Qt\\Tools\\mingw1120_64\\lib\\gcc\\x86_64-w64-mingw32\\11.2.0\\include\\c++","-isystem","C:\\Qt\\Tools\\mingw1120_64\\lib\\gcc\\x86_64-w64-mingw32\\11.2.0\\include\\c++\\x86_64-w64-mingw32","-isystem","C:\\Qt\\Tools\\mingw1120_64\\lib\\gcc\\x86_64-w64-mingw32\\11.2.0\\include\\c++\\backward","-isystem","C:\\Qt\\Tools\\QtCreator\\bin\\clang\\lib\\clang\\17\\include","-isystem","C:\\Qt\\Tools\\mingw1120_64\\x86_64-w64-mingw32\\include","-fmessage-length=0","-fdiagnostics-show-note-include-stack","-fretain-comments-from-system-headers","-fmacro-backtrace-limit=0","-ferror-limit=1000","-x","c++","D:\\Qt\\Project\\EntryPage\\dialogsetgameboard.cpp"],"directory":"D:/Qt/Project/EntryPage/build/Desktop_Qt_6_6_3_MinGW_64_bit-Debug/.qtc_clangd","file":"D:/Qt/Project/EntryPage/dialogsetgameboard.cpp"},{"arguments":["clang","-Wno-documentation-unknown-command","-Wno-unknown-warning-option","-Wno-unknown-pragmas","-nostdinc","-nostdinc++","-g","-Wall","-Wextra","-Wextra","-fexceptions","-mthreads","-fsyntax-only","-m64","--target=x86_64-w64-mingw32","-std=gnu++17","-DUNICODE","-D_UNICODE","-DWIN32","-DMINGW_HAS_SECURE_API","-DQT_QML_DEBUG","-DQT_WIDGETS_LIB","-DQT_MULTIMEDIA_LIB","-DQT_GUI_LIB","-DQT_NETWORK_LIB","-DQT_CORE_LIB","-DQT_NEEDS_QMAIN","-DQ_CREATOR_RUN","-DQT_ANNOTATE_FUNCTION(x)=__attribute__((annotate(#x)))","-IC:\\Qt\\Tools\\QtCreator\\share\\qtcreator\\cplusplus\\wrappedMingwHeaders","-IC:\\Qt\\Tools\\QtCreator\\share\\qtcreator\\cplusplus\\wrappedQtHeaders","-IC:\\Qt\\Tools\\QtCreator\\share\\qtcreator\\cplusplus\\wrappedQtHeaders\\QtCore","-ID:\\Qt\\Project\\EntryPage","-IC:\\Qt\\6.6.3\\mingw_64\\include","-IC:\\Qt\\6.6.3\\mingw_64\\include\\QtWidgets","-IC:\\Qt\\6.6.3\\mingw_64\\include\\QtMultimedia","-IC:\\Qt\\6.6.3\\mingw_64\\include\\QtGui","-IC:\\Qt\\6.6.3\\mingw_64\\include\\QtNetwork","-IC:\\Qt\\6.6.3\\mingw_64\\include\\QtCore","-ID:\\Qt\\Project\\EntryPage\\build\\Desktop_Qt_6_6_3_MinGW_64_bit-Debug\\debug","-ID:\\Qt\\Project\\EntryPage\\build\\Desktop_Qt_6_6_3_MinGW_64_bit-Debug","-IC:\\Qt\\6.6.3\\mingw_64\\mkspecs\\win32-g++","-isystem","C:\\Qt\\Tools\\mingw1120_64\\lib\\gcc\\x86_64-w64-mingw32\\11.2.0\\include\\c++","-isystem","C:\\Qt\\Tools\\mingw1120_64\\lib\\gcc\\x86_64-w64-mingw32\\11.2.0\\include\\c++\\x86_64-w64-mingw32","-isystem","C:\\Qt\\Tools\\mingw1120_64\\lib\\gcc\\x86_64-w64-mingw32\\11.2.0\\include\\c++\\backward","-isystem","C:\\Qt\\Tools\\QtCreator\\bin\\clang\\lib\\clang\\17\\include","-isystem","C:\\Qt\\Tools\\mingw1120_64\\x86_64-w64-mingw32\\include","-fmessage-length=0","-fdiagnostics-show-note-include-stack","-fretain-comments-from-system-headers","-fmacro-backtrace-limit=0","-ferror-limit=1000","-x","c++","D:\\Qt\\Project\\EntryPage\\draggablebutton.cpp"],"directory":"D:/Qt/Project/EntryPage/build/Desktop_Qt_6_6_3_MinGW_64_bit-Debug/.qtc_clangd","file":"D:/Qt/Project/EntryPage/draggablebutton.cpp"},{"arguments":["clang","-Wno-documentation-unknown-command","-Wno-unknown-warning-option","-Wno-unknown-pragmas","-nostdinc","-nostdinc++","-g","-Wall","-Wextra","-Wextra","-fexceptions","-mthreads","-fsyntax-only","-m64","--target=x86_64-w64-mingw32","-std=gnu++17","-DUNICODE","-D_UNICODE","-DWIN32","-DMINGW_HAS_SECURE_API","-DQT_QML_DEBUG","-DQT_WIDGETS_LIB","-DQT_MULTIMEDIA_LIB","-DQT_GUI_LIB","-DQT_NETWORK_LIB","-DQT_CORE_LIB","-DQT_NEEDS_QMAIN","-DQ_CREATOR_RUN","-DQT_ANNOTATE_FUNCTION(x)=__attribute__((annotate(#x)))","-IC:\\Qt\\Tools\\QtCreator\\share\\qtcreator\\cplusplus\\wrappedMingwHeaders","-IC:\\Qt\\Tools\\QtCreator\\share\\qtcreator\\cplusplus\\wrappedQtHeaders","-IC:\\Qt\\Tools\\QtCreator\\share\\qtcreator\\cplusplus\\wrappedQtHeaders\\QtCore","-ID:\\Qt\\Project\\EntryPage","-IC:\\Qt\\6.6.3\\mingw_64\\include","-IC:\\Qt\\6.6.3\\mingw_64\\include\\QtWidgets","-IC:\\Qt\\6.6.3\\mingw_64\\include\\QtMultimedia","-IC:\\Qt\\6.6.3\\mingw_64\\include\\QtGui","-IC:\\Qt\\6.6.3\\mingw_64\\include\\QtNetwork","-IC:\\Qt\\6.6.3\\mingw_64\\include\\QtCore","-ID:\\Qt\\Project\\EntryPage\\build\\Desktop_Qt_6_6_3_MinGW_64_bit-Debug\\debug","-ID:\\Qt\\Project\\EntryPage\\build\\Desktop_Qt_6_6_3_MinGW_64_bit-Debug","-IC:\\Qt\\6.6.3\\mingw_64\\mkspecs\\win32-g++","-isystem","C:\\Qt\\Tools\\mingw1120_64\\lib\\gcc\\x86_64-w64-mingw32\\11.2.0\\include\\c++","-isystem","C:\\Qt\\Tools\\mingw1120_64\\lib\\gcc\\x86_64-w64-mingw32\\11.2.0\\include\\c++\\x86_64-w64-mingw32","-isystem","C:\\Qt\\Tools\\mingw1120_64\\lib\\gcc\\x86_64-w64-mingw32\\11.2.0\\include\\c++\\backward","-isystem","C:\\Qt\\Tools\\QtCreator\\bin\\clang\\lib\\clang\\17\\include","-isystem","C:\\Qt\\Tools\\mingw1120_64\\x86_64-w64-mingw32\\include","-fmessage-length=0","-fdiagnostics-show-note-include-stack","-fretain-comments-from-system-headers","-fmacro-backtrace-limit=0","-ferror-limit=1000","-x","c++","D:\\Qt\\Project\\EntryPage\\gameboard.cpp"],"directory":"D:/Qt/Project/EntryPage/build/Desktop_Qt_6_6_3_MinGW_64_bit-Debug/.qtc_clangd","file":"D:/Qt/Project/EntryPage/gameboard.cpp"},{"arguments":["clang","-Wno-documentation-unknown-command","-Wno-unknown-warning-option","-Wno-unknown-pragmas","-nostdinc","-nostdinc++","-g","-Wall","-Wextra","-Wextra","-fexceptions","-mthreads","-fsyntax-only","-m64","--target=x86_64-w64-mingw32","-std=gnu++17","-DUNICODE","-D_UNICODE","-DWIN32","-DMINGW_HAS_SECURE_API","-DQT_QML_DEBUG","-DQT_WIDGETS_LIB","-DQT_MULTIMEDIA_LIB","-DQT_GUI_LIB","-DQT_NETWORK_LIB","-DQT_CORE_LIB","-DQT_NEEDS_QMAIN","-DQ_CREATOR_RUN","-DQT_ANNOTATE_FUNCTION(x)=__attribute__((annotate(#x)))","-IC:\\Qt\\Tools\\QtCreator\\share\\qtcreator\\cplusplus\\wrappedMingwHeaders","-IC:\\Qt\\Tools\\QtCreator\\share\\qtcreator\\cplusplus\\wrappedQtHeaders","-IC:\\Qt\\Tools\\QtCreator\\share\\qtcreator\\cplusplus\\wrappedQtHeaders\\QtCore","-ID:\\Qt\\Project\\EntryPage","-IC:\\Qt\\6.6.3\\mingw_64\\include","-IC:\\Qt\\6.6.3\\mingw_64\\include\\QtWidgets","-IC:\\Qt\\6.6.3\\mingw_64\\include\\QtMultimedia","-IC:\\Qt\\6.6.3\\mingw_64\\include\\QtGui","-IC:\\Qt\\6.6.3\\mingw_64\\include\\QtNetwork","-IC:\\Qt\\6.6.3\\mingw_64\\include\\QtCore","-ID:\\Qt\\Project\\EntryPage\\build\\Desktop_Qt_6_6_3_MinGW_64_bit-Debug\\debug","-ID:\\Qt\\Project\\EntryPage\\build\\Desktop_Qt_6_6_3_MinGW_64_bit-Debug","-IC:\\Qt\\6.6.3\\mingw_64\\mkspecs\\win32-g++","-isystem","C:\\Qt\\Tools\\mingw1120_64\\lib\\gcc\\x86_64-w64-mingw32\\11.2.0\\include\\c++","-isystem","C:\\Qt\\Tools\\mingw1120_64\\lib\\gcc\\x86_64-w64-mingw32\\11.2.0\\include\\c++\\x86_64-w64-mingw32","-isystem","C:\\Qt\\Tools\\mingw1120_64\\lib\\gcc\\x86_64-w64-mingw32\\11.2.0\\include\\c++\\backward","-isystem","C:\\Qt\\Tools\\QtCreator\\bin\\clang\\lib\\clang\\17\\include","-isystem","C:\\Qt\\Tools\\mingw1120_64\\x86_64-w64-mingw32\\include","-fmessage-length=0","-fdiagnostics-show-note-include-stack","-fretain-comments-from-system-headers","-fmacro-backtrace-limit=0","-ferror-limit=1000","-x","c++","D:\\Qt\\Project\\EntryPage\\hashpassword.cpp"],"directory":"D:/Qt/Project/EntryPage/build/Desktop_Qt_6_6_3_MinGW_64_bit-Debug/.qtc_clangd","file":"D:/Qt/Project/EntryPage/hashpassword.cpp"},{"arguments":["clang","-Wno-documentation-unknown-command","-Wno-unknown-warning-option","-Wno-unknown-pragmas","-nostdinc","-nostdinc++","-g","-Wall","-Wextra","-Wextra","-fexceptions","-mthreads","-fsyntax-only","-m64","--target=x86_64-w64-mingw32","-std=gnu++17","-DUNICODE","-D_UNICODE","-DWIN32","-DMINGW_HAS_SECURE_API","-DQT_QML_DEBUG","-DQT_WIDGETS_LIB","-DQT_MULTIMEDIA_LIB","-DQT_GUI_LIB","-DQT_NETWORK_LIB","-DQT_CORE_LIB","-DQT_NEEDS_QMAIN","-DQ_CREATOR_RUN","-DQT_ANNOTATE_FUNCTION(x)=__attribute__((annotate(#x)))","-IC:\\Qt\\Tools\\QtCreator\\share\\qtcreator\\cplusplus\\wrappedMingwHeaders","-IC:\\Qt\\Tools\\QtCreator\\share\\qtcreator\\cplusplus\\wrappedQtHeaders","-IC:\\Qt\\Tools\\QtCreator\\share\\qtcreator\\cplusplus\\wrappedQtHeaders\\QtCore","-ID:\\Qt\\Project\\EntryPage","-IC:\\Qt\\6.6.3\\mingw_64\\include","-IC:\\Qt\\6.6.3\\mingw_64\\include\\QtWidgets","-IC:\\Qt\\6.6.3\\mingw_64\\include\\QtMultimedia","-IC:\\Qt\\6.6.3\\mingw_64\\include\\QtGui","-IC:\\Qt\\6.6.3\\mingw_64\\include\\QtNetwork","-IC:\\Qt\\6.6.3\\mingw_64\\include\\QtCore","-ID:\\Qt\\Project\\EntryPage\\build\\Desktop_Qt_6_6_3_MinGW_64_bit-Debug\\debug","-ID:\\Qt\\Project\\EntryPage\\build\\Desktop_Qt_6_6_3_MinGW_64_bit-Debug","-IC:\\Qt\\6.6.3\\mingw_64\\mkspecs\\win32-g++","-isystem","C:\\Qt\\Tools\\mingw1120_64\\lib\\gcc\\x86_64-w64-mingw32\\11.2.0\\include\\c++","-isystem","C:\\Qt\\Tools\\mingw1120_64\\lib\\gcc\\x86_64-w64-mingw32\\11.2.0\\include\\c++\\x86_64-w64-mingw32","-isystem","C:\\Qt\\Tools\\mingw1120_64\\lib\\gcc\\x86_64-w64-mingw32\\11.2.0\\include\\c++\\backward","-isystem","C:\\Qt\\Tools\\QtCreator\\bin\\clang\\lib\\clang\\17\\include","-isystem","C:\\Qt\\Tools\\mingw1120_64\\x86_64-w64-mingw32\\include","-fmessage-length=0","-fdiagnostics-show-note-include-stack","-fretain-comments-from-system-headers","-fmacro-backtrace-limit=0","-ferror-limit=1000","-x","c++","D:\\Qt\\Project\\EntryPage\\main.cpp"],"directory":"D:/Qt/Project/EntryPage/build/Desktop_Qt_6_6_3_MinGW_64_bit-Debug/.qtc_clangd","file":"D:/Qt/Project/EntryPage/main.cpp"},{"arguments":["clang","-Wno-documentation-unknown-command","-Wno-unknown-warning-option","-Wno-unknown-pragmas","-nostdinc","-nostdinc++","-g","-Wall","-Wextra","-Wextra","-fexceptions","-mthreads","-fsyntax-only","-m64","--target=x86_64-w64-mingw32","-std=gnu++17","-DUNICODE","-D_UNICODE","-DWIN32","-DMINGW_HAS_SECURE_API","-DQT_QML_DEBUG","-DQT_WIDGETS_LIB","-DQT_MULTIMEDIA_LIB","-DQT_GUI_LIB","-DQT_NETWORK_LIB","-DQT_CORE_LIB","-DQT_NEEDS_QMAIN","-DQ_CREATOR_RUN","-DQT_ANNOTATE_FUNCTION(x)=__attribute__((annotate(#x)))","-IC:\\Qt\\Tools\\QtCreator\\share\\qtcreator\\cplusplus\\wrappedMingwHeaders","-IC:\\Qt\\Tools\\QtCreator\\share\\qtcreator\\cplusplus\\wrappedQtHeaders","-IC:\\Qt\\Tools\\QtCreator\\share\\qtcreator\\cplusplus\\wrappedQtHeaders\\QtCore","-ID:\\Qt\\Project\\EntryPage","-IC:\\Qt\\6.6.3\\mingw_64\\include","-IC:\\Qt\\6.6.3\\mingw_64\\include\\QtWidgets","-IC:\\Qt\\6.6.3\\mingw_64\\include\\QtMultimedia","-IC:\\Qt\\6.6.3\\mingw_64\\include\\QtGui","-IC:\\Qt\\6.6.3\\mingw_64\\include\\QtNetwork","-IC:\\Qt\\6.6.3\\mingw_64\\include\\QtCore","-ID:\\Qt\\Project\\EntryPage\\build\\Desktop_Qt_6_6_3_MinGW_64_bit-Debug\\debug","-ID:\\Qt\\Project\\EntryPage\\build\\Desktop_Qt_6_6_3_MinGW_64_bit-Debug","-IC:\\Qt\\6.6.3\\mingw_64\\mkspecs\\win32-g++","-isystem","C:\\Qt\\Tools\\mingw1120_64\\lib\\gcc\\x86_64-w64-mingw32\\11.2.0\\include\\c++","-isystem","C:\\Qt\\Tools\\mingw1120_64\\lib\\gcc\\x86_64-w64-mingw32\\11.2.0\\include\\c++\\x86_64-w64-mingw32","-isystem","C:\\Qt\\Tools\\mingw1120_64\\lib\\gcc\\x86_64-w64-mingw32\\11.2.0\\include\\c++\\backward","-isystem","C:\\Qt\\Tools\\QtCreator\\bin\\clang\\lib\\clang\\17\\include","-isystem","C:\\Qt\\Tools\\mingw1120_64\\x86_64-w64-mingw32\\include","-fmessage-length=0","-fdiagnostics-show-note-include-stack","-fretain-comments-from-system-headers","-fmacro-backtrace-limit=0","-ferror-limit=1000","-x","c++","D:\\Qt\\Project\\EntryPage\\mainwindow.cpp"],"directory":"D:/Qt/Project/EntryPage/build/Desktop_Qt_6_6_3_MinGW_64_bit-Debug/.qtc_clangd","file":"D:/Qt/Project/EntryPage/mainwindow.cpp"},{"arguments":["clang","-Wno-documentation-unknown-command","-Wno-unknown-warning-option","-Wno-unknown-pragmas","-nostdinc","-nostdinc++","-g","-Wall","-Wextra","-Wextra","-fexceptions","-mthreads","-fsyntax-only","-m64","--target=x86_64-w64-mingw32","-std=gnu++17","-DUNICODE","-D_UNICODE","-DWIN32","-DMINGW_HAS_SECURE_API","-DQT_QML_DEBUG","-DQT_WIDGETS_LIB","-DQT_MULTIMEDIA_LIB","-DQT_GUI_LIB","-DQT_NETWORK_LIB","-DQT_CORE_LIB","-DQT_NEEDS_QMAIN","-DQ_CREATOR_RUN","-DQT_ANNOTATE_FUNCTION(x)=__attribute__((annotate(#x)))","-IC:\\Qt\\Tools\\QtCreator\\share\\qtcreator\\cplusplus\\wrappedMingwHeaders","-IC:\\Qt\\Tools\\QtCreator\\share\\qtcreator\\cplusplus\\wrappedQtHeaders","-IC:\\Qt\\Tools\\QtCreator\\share\\qtcreator\\cplusplus\\wrappedQtHeaders\\QtCore","-ID:\\Qt\\Project\\EntryPage","-IC:\\Qt\\6.6.3\\mingw_64\\include","-IC:\\Qt\\6.6.3\\mingw_64\\include\\QtWidgets","-IC:\\Qt\\6.6.3\\mingw_64\\include\\QtMultimedia","-IC:\\Qt\\6.6.3\\mingw_64\\include\\QtGui","-IC:\\Qt\\6.6.3\\mingw_64\\include\\QtNetwork","-IC:\\Qt\\6.6.3\\mingw_64\\include\\QtCore","-ID:\\Qt\\Project\\EntryPage\\build\\Desktop_Qt_6_6_3_MinGW_64_bit-Debug\\debug","-ID:\\Qt\\Project\\EntryPage\\build\\Desktop_Qt_6_6_3_MinGW_64_bit-Debug","-IC:\\Qt\\6.6.3\\mingw_64\\mkspecs\\win32-g++","-isystem","C:\\Qt\\Tools\\mingw1120_64\\lib\\gcc\\x86_64-w64-mingw32\\11.2.0\\include\\c++","-isystem","C:\\Qt\\Tools\\mingw1120_64\\lib\\gcc\\x86_64-w64-mingw32\\11.2.0\\include\\c++\\x86_64-w64-mingw32","-isystem","C:\\Qt\\Tools\\mingw1120_64\\lib\\gcc\\x86_64-w64-mingw32\\11.2.0\\include\\c++\\backward","-isystem","C:\\Qt\\Tools\\QtCreator\\bin\\clang\\lib\\clang\\17\\include","-isystem","C:\\Qt\\Tools\\mingw1120_64\\x86_64-w64-mingw32\\include","-fmessage-length=0","-fdiagnostics-show-note-include-stack","-fretain-comments-from-system-headers","-fmacro-backtrace-limit=0","-ferror-limit=1000","-x","c++","D:\\Qt\\Project\\EntryPage\\dialogloginclicked.cpp"],"directory":"D:/Qt/Project/EntryPage/build/Desktop_Qt_6_6_3_MinGW_64_bit-Debug/.qtc_clangd","file":"D:/Qt/Project/EntryPage/dialogloginclicked.cpp"},{"arguments":["clang","-Wno-documentation-unknown-command","-Wno-unknown-warning-option","-Wno-unknown-pragmas","-nostdinc","-nostdinc++","-g","-Wall","-Wextra","-Wextra","-fexceptions","-mthreads","-fsyntax-only","-m64","--target=x86_64-w64-mingw32","-std=gnu++17","-DUNICODE","-D_UNICODE","-DWIN32","-DMINGW_HAS_SECURE_API","-DQT_QML_DEBUG","-DQT_WIDGETS_LIB","-DQT_MULTIMEDIA_LIB","-DQT_GUI_LIB","-DQT_NETWORK_LIB","-DQT_CORE_LIB","-DQT_NEEDS_QMAIN","-DQ_CREATOR_RUN","-DQT_ANNOTATE_FUNCTION(x)=__attribute__((annotate(#x)))","-IC:\\Qt\\Tools\\QtCreator\\share\\qtcreator\\cplusplus\\wrappedMingwHeaders","-IC:\\Qt\\Tools\\QtCreator\\share\\qtcreator\\cplusplus\\wrappedQtHeaders","-IC:\\Qt\\Tools\\QtCreator\\share\\qtcreator\\cplusplus\\wrappedQtHeaders\\QtCore","-ID:\\Qt\\Project\\EntryPage","-IC:\\Qt\\6.6.3\\mingw_64\\include","-IC:\\Qt\\6.6.3\\mingw_64\\include\\QtWidgets","-IC:\\Qt\\6.6.3\\mingw_64\\include\\QtMultimedia","-IC:\\Qt\\6.6.3\\mingw_64\\include\\QtGui","-IC:\\Qt\\6.6.3\\mingw_64\\include\\QtNetwork","-IC:\\Qt\\6.6.3\\mingw_64\\include\\QtCore","-ID:\\Qt\\Project\\EntryPage\\build\\Desktop_Qt_6_6_3_MinGW_64_bit-Debug\\debug","-ID:\\Qt\\Project\\EntryPage\\build\\Desktop_Qt_6_6_3_MinGW_64_bit-Debug","-IC:\\Qt\\6.6.3\\mingw_64\\mkspecs\\win32-g++","-isystem","C:\\Qt\\Tools\\mingw1120_64\\lib\\gcc\\x86_64-w64-mingw32\\11.2.0\\include\\c++","-isystem","C:\\Qt\\Tools\\mingw1120_64\\lib\\gcc\\x86_64-w64-mingw32\\11.2.0\\include\\c++\\x86_64-w64-mingw32","-isystem","C:\\Qt\\Tools\\mingw1120_64\\lib\\gcc\\x86_64-w64-mingw32\\11.2.0\\include\\c++\\backward","-isystem","C:\\Qt\\Tools\\QtCreator\\bin\\clang\\lib\\clang\\17\\include","-isystem","C:\\Qt\\Tools\\mingw1120_64\\x86_64-w64-mingw32\\include","-fmessage-length=0","-fdiagnostics-show-note-include-stack","-fretain-comments-from-system-headers","-fmacro-backtrace-limit=0","-ferror-limit=1000","-x","c++","D:\\Qt\\Project\\EntryPage\\dialogsignupclicked.cpp"],"directory":"D:/Qt/Project/EntryPage/build/Desktop_Qt_6_6_3_MinGW_64_bit-Debug/.qtc_clangd","file":"D:/Qt/Project/EntryPage/dialogsignupclicked.cpp"},{"arguments":["clang","-Wno-documentation-unknown-command","-Wno-unknown-warning-option","-Wno-unknown-pragmas","-nostdinc","-nostdinc++","-g","-Wall","-Wextra","-Wextra","-fexceptions","-mthreads","-fsyntax-only","-m64","--target=x86_64-w64-mingw32","-std=gnu++17","-DUNICODE","-D_UNICODE","-DWIN32","-DMINGW_HAS_SECURE_API","-DQT_QML_DEBUG","-DQT_WIDGETS_LIB","-DQT_MULTIMEDIA_LIB","-DQT_GUI_LIB","-DQT_NETWORK_LIB","-DQT_CORE_LIB","-DQT_NEEDS_QMAIN","-DQ_CREATOR_RUN","-DQT_ANNOTATE_FUNCTION(x)=__attribute__((annotate(#x)))","-IC:\\Qt\\Tools\\QtCreator\\share\\qtcreator\\cplusplus\\wrappedMingwHeaders","-IC:\\Qt\\Tools\\QtCreator\\share\\qtcreator\\cplusplus\\wrappedQtHeaders","-IC:\\Qt\\Tools\\QtCreator\\share\\qtcreator\\cplusplus\\wrappedQtHeaders\\QtCore","-ID:\\Qt\\Project\\EntryPage","-IC:\\Qt\\6.6.3\\mingw_64\\include","-IC:\\Qt\\6.6.3\\mingw_64\\include\\QtWidgets","-IC:\\Qt\\6.6.3\\mingw_64\\include\\QtMultimedia","-IC:\\Qt\\6.6.3\\mingw_64\\include\\QtGui","-IC:\\Qt\\6.6.3\\mingw_64\\include\\QtNetwork","-IC:\\Qt\\6.6.3\\mingw_64\\include\\QtCore","-ID:\\Qt\\Project\\EntryPage\\build\\Desktop_Qt_6_6_3_MinGW_64_bit-Debug\\debug","-ID:\\Qt\\Project\\EntryPage\\build\\Desktop_Qt_6_6_3_MinGW_64_bit-Debug","-IC:\\Qt\\6.6.3\\mingw_64\\mkspecs\\win32-g++","-isystem","C:\\Qt\\Tools\\mingw1120_64\\lib\\gcc\\x86_64-w64-mingw32\\11.2.0\\include\\c++","-isystem","C:\\Qt\\Tools\\mingw1120_64\\lib\\gcc\\x86_64-w64-mingw32\\11.2.0\\include\\c++\\x86_64-w64-mingw32","-isystem","C:\\Qt\\Tools\\mingw1120_64\\lib\\gcc\\x86_64-w64-mingw32\\11.2.0\\include\\c++\\backward","-isystem","C:\\Qt\\Tools\\QtCreator\\bin\\clang\\lib\\clang\\17\\include","-isystem","C:\\Qt\\Tools\\mingw1120_64\\x86_64-w64-mingw32\\include","-fmessage-length=0","-fdiagnostics-show-note-include-stack","-fretain-comments-from-system-headers","-fmacro-backtrace-limit=0","-ferror-limit=1000","-x","c++","D:\\Qt\\Project\\EntryPage\\musicplayer.cpp"],"directory":"D:/Qt/Project/EntryPage/build/Desktop_Qt_6_6_3_MinGW_64_bit-Debug/.qtc_clangd","file":"D:/Qt/Project/EntryPage/musicplayer.cpp"},{"arguments":["clang","-Wno-documentation-unknown-command","-Wno-unknown-warning-option","-Wno-unknown-pragmas","-nostdinc","-nostdinc++","-g","-Wall","-Wextra","-Wextra","-fexceptions","-mthreads","-fsyntax-only","-m64","--target=x86_64-w64-mingw32","-std=gnu++17","-DUNICODE","-D_UNICODE","-DWIN32","-DMINGW_HAS_SECURE_API","-DQT_QML_DEBUG","-DQT_WIDGETS_LIB","-DQT_MULTIMEDIA_LIB","-DQT_GUI_LIB","-DQT_NETWORK_LIB","-DQT_CORE_LIB","-DQT_NEEDS_QMAIN","-DQ_CREATOR_RUN","-DQT_ANNOTATE_FUNCTION(x)=__attribute__((annotate(#x)))","-IC:\\Qt\\Tools\\QtCreator\\share\\qtcreator\\cplusplus\\wrappedMingwHeaders","-IC:\\Qt\\Tools\\QtCreator\\share\\qtcreator\\cplusplus\\wrappedQtHeaders","-IC:\\Qt\\Tools\\QtCreator\\share\\qtcreator\\cplusplus\\wrappedQtHeaders\\QtCore","-ID:\\Qt\\Project\\EntryPage","-IC:\\Qt\\6.6.3\\mingw_64\\include","-IC:\\Qt\\6.6.3\\mingw_64\\include\\QtWidgets","-IC:\\Qt\\6.6.3\\mingw_64\\include\\QtMultimedia","-IC:\\Qt\\6.6.3\\mingw_64\\include\\QtGui","-IC:\\Qt\\6.6.3\\mingw_64\\include\\QtNetwork","-IC:\\Qt\\6.6.3\\mingw_64\\include\\QtCore","-ID:\\Qt\\Project\\EntryPage\\build\\Desktop_Qt_6_6_3_MinGW_64_bit-Debug\\debug","-ID:\\Qt\\Project\\EntryPage\\build\\Desktop_Qt_6_6_3_MinGW_64_bit-Debug","-IC:\\Qt\\6.6.3\\mingw_64\\mkspecs\\win32-g++","-isystem","C:\\Qt\\Tools\\mingw1120_64\\lib\\gcc\\x86_64-w64-mingw32\\11.2.0\\include\\c++","-isystem","C:\\Qt\\Tools\\mingw1120_64\\lib\\gcc\\x86_64-w64-mingw32\\11.2.0\\include\\c++\\x86_64-w64-mingw32","-isystem","C:\\Qt\\Tools\\mingw1120_64\\lib\\gcc\\x86_64-w64-mingw32\\11.2.0\\include\\c++\\backward","-isystem","C:\\Qt\\Tools\\QtCreator\\bin\\clang\\lib\\clang\\17\\include","-isystem","C:\\Qt\\Tools\\mingw1120_64\\x86_64-w64-mingw32\\include","-fmessage-length=0","-fdiagnostics-show-note-include-stack","-fretain-comments-from-system-headers","-fmacro-backtrace-limit=0","-ferror-limit=1000","-x","c++","D:\\Qt\\Project\\EntryPage\\ship.cpp"],"directory":"D:/Qt/Project/EntryPage/build/Desktop_Qt_6_6_3_MinGW_64_bit-Debug/.qtc_clangd","file":"D:/Qt/Project/EntryPage/ship.cpp"},{"arguments":["clang","-Wno-documentation-unknown-command","-Wno-unknown-warning-option","-Wno-unknown-pragmas","-nostdinc","-nostdinc++","-g","-Wall","-Wextra","-Wextra","-fexceptions","-mthreads","-fsyntax-only","-m64","--target=x86_64-w64-mingw32","-std=gnu++17","-DUNICODE","-D_UNICODE","-DWIN32","-DMINGW_HAS_SECURE_API","-DQT_QML_DEBUG","-DQT_WIDGETS_LIB","-DQT_MULTIMEDIA_LIB","-DQT_GUI_LIB","-DQT_NETWORK_LIB","-DQT_CORE_LIB","-DQT_NEEDS_QMAIN","-DQ_CREATOR_RUN","-DQT_ANNOTATE_FUNCTION(x)=__attribute__((annotate(#x)))","-IC:\\Qt\\Tools\\QtCreator\\share\\qtcreator\\cplusplus\\wrappedMingwHeaders","-IC:\\Qt\\Tools\\QtCreator\\share\\qtcreator\\cplusplus\\wrappedQtHeaders","-IC:\\Qt\\Tools\\QtCreator\\share\\qtcreator\\cplusplus\\wrappedQtHeaders\\QtCore","-ID:\\Qt\\Project\\EntryPage","-IC:\\Qt\\6.6.3\\mingw_64\\include","-IC:\\Qt\\6.6.3\\mingw_64\\include\\QtWidgets","-IC:\\Qt\\6.6.3\\mingw_64\\include\\QtMultimedia","-IC:\\Qt\\6.6.3\\mingw_64\\include\\QtGui","-IC:\\Qt\\6.6.3\\mingw_64\\include\\QtNetwork","-IC:\\Qt\\6.6.3\\mingw_64\\include\\QtCore","-ID:\\Qt\\Project\\EntryPage\\build\\Desktop_Qt_6_6_3_MinGW_64_bit-Debug\\debug","-ID:\\Qt\\Project\\EntryPage\\build\\Desktop_Qt_6_6_3_MinGW_64_bit-Debug","-IC:\\Qt\\6.6.3\\mingw_64\\mkspecs\\win32-g++","-isystem","C:\\Qt\\Tools\\mingw1120_64\\lib\\gcc\\x86_64-w64-mingw32\\11.2.0\\include\\c++","-isystem","C:\\Qt\\Tools\\mingw1120_64\\lib\\gcc\\x86_64-w64-mingw32\\11.2.0\\include\\c++\\x86_64-w64-mingw32","-isystem","C:\\Qt\\Tools\\mingw1120_64\\lib\\gcc\\x86_64-w64-mingw32\\11.2.0\\include\\c++\\backward","-isystem","C:\\Qt\\Tools\\QtCreator\\bin\\clang\\lib\\clang\\17\\include","-isystem","C:\\Qt\\Tools\\mingw1120_64\\x86_64-w64-mingw32\\include","-fmessage-length=0","-fdiagnostics-show-note-include-stack","-fretain-comments-from-system-headers","-fmacro-backtrace-limit=0","-ferror-limit=1000","-x","c++","D:\\Qt\\Project\\EntryPage\\user.cpp"],"directory":"D:/Qt/Project/EntryPage/build/Desktop_Qt_6_6_3_MinGW_64_bit-Debug/.qtc_clangd","file":"D:/Qt/Project/EntryPage/user.cpp"},{"arguments":["clang","-Wno-documentation-unknown-command","-Wno-unknown-warning-option","-Wno-unknown-pragmas","-nostdinc","-nostdinc++","-g","-Wall","-Wextra","-Wextra","-fexceptions","-mthreads","-fsyntax-only","-m64","--target=x86_64-w64-mingw32","-std=gnu++17","-DUNICODE","-D_UNICODE","-DWIN32","-DMINGW_HAS_SECURE_API","-DQT_QML_DEBUG","-DQT_WIDGETS_LIB","-DQT_MULTIMEDIA_LIB","-DQT_GUI_LIB","-DQT_NETWORK_LIB","-DQT_CORE_LIB","-DQT_NEEDS_QMAIN","-DQ_CREATOR_RUN","-DQT_ANNOTATE_FUNCTION(x)=__attribute__((annotate(#x)))","-IC:\\Qt\\Tools\\QtCreator\\share\\qtcreator\\cplusplus\\wrappedMingwHeaders","-IC:\\Qt\\Tools\\QtCreator\\share\\qtcreator\\cplusplus\\wrappedQtHeaders","-IC:\\Qt\\Tools\\QtCreator\\share\\qtcreator\\cplusplus\\wrappedQtHeaders\\QtCore","-ID:\\Qt\\Project\\EntryPage","-IC:\\Qt\\6.6.3\\mingw_64\\include","-IC:\\Qt\\6.6.3\\mingw_64\\include\\QtWidgets","-IC:\\Qt\\6.6.3\\mingw_64\\include\\QtMultimedia","-IC:\\Qt\\6.6.3\\mingw_64\\include\\QtGui","-IC:\\Qt\\6.6.3\\mingw_64\\include\\QtNetwork","-IC:\\Qt\\6.6.3\\mingw_64\\include\\QtCore","-ID:\\Qt\\Project\\EntryPage\\build\\Desktop_Qt_6_6_3_MinGW_64_bit-Debug\\debug","-ID:\\Qt\\Project\\EntryPage\\build\\Desktop_Qt_6_6_3_MinGW_64_bit-Debug","-IC:\\Qt\\6.6.3\\mingw_64\\mkspecs\\win32-g++","-isystem","C:\\Qt\\Tools\\mingw1120_64\\lib\\gcc\\x86_64-w64-mingw32\\11.2.0\\include\\c++","-isystem","C:\\Qt\\Tools\\mingw1120_64\\lib\\gcc\\x86_64-w64-mingw32\\11.2.0\\include\\c++\\x86_64-w64-mingw32","-isystem","C:\\Qt\\Tools\\mingw1120_64\\lib\\gcc\\x86_64-w64-mingw32\\11.2.0\\include\\c++\\backward","-isystem","C:\\Qt\\Tools\\QtCreator\\bin\\clang\\lib\\clang\\17\\include","-isystem","C:\\Qt\\Tools\\mingw1120_64\\x86_64-w64-mingw32\\include","-fmessage-length=0","-fdiagnostics-show-note-include-stack","-fretain-comments-from-system-headers","-fmacro-backtrace-limit=0","-ferror-limit=1000","-x","c++","D:\\Qt\\Project\\EntryPage\\validator.cpp"],"directory":"D:/Qt/Project/EntryPage/build/Desktop_Qt_6_6_3_MinGW_64_bit-Debug/.qtc_clangd","file":"D:/Qt/Project/EntryPage/validator.cpp"},{"arguments":["clang","-Wno-documentation-unknown-command","-Wno-unknown-warning-option","-Wno-unknown-pragmas","-nostdinc","-nostdinc++","-g","-Wall","-Wextra","-Wextra","-fexceptions","-mthreads","-fsyntax-only","-m64","--target=x86_64-w64-mingw32","-std=gnu++17","-DUNICODE","-D_UNICODE","-DWIN32","-DMINGW_HAS_SECURE_API","-DQT_QML_DEBUG","-DQT_WIDGETS_LIB","-DQT_MULTIMEDIA_LIB","-DQT_GUI_LIB","-DQT_NETWORK_LIB","-DQT_CORE_LIB","-DQT_NEEDS_QMAIN","-DQ_CREATOR_RUN","-DQT_ANNOTATE_FUNCTION(x)=__attribute__((annotate(#x)))","-IC:\\Qt\\Tools\\QtCreator\\share\\qtcreator\\cplusplus\\wrappedMingwHeaders","-IC:\\Qt\\Tools\\QtCreator\\share\\qtcreator\\cplusplus\\wrappedQtHeaders","-IC:\\Qt\\Tools\\QtCreator\\share\\qtcreator\\cplusplus\\wrappedQtHeaders\\QtCore","-ID:\\Qt\\Project\\EntryPage","-IC:\\Qt\\6.6.3\\mingw_64\\include","-IC:\\Qt\\6.6.3\\mingw_64\\include\\QtWidgets","-IC:\\Qt\\6.6.3\\mingw_64\\include\\QtMultimedia","-IC:\\Qt\\6.6.3\\mingw_64\\include\\QtGui","-IC:\\Qt\\6.6.3\\mingw_64\\include\\QtNetwork","-IC:\\Qt\\6.6.3\\mingw_64\\include\\QtCore","-ID:\\Qt\\Project\\EntryPage\\build\\Desktop_Qt_6_6_3_MinGW_64_bit-Debug\\debug","-ID:\\Qt\\Project\\EntryPage\\build\\Desktop_Qt_6_6_3_MinGW_64_bit-Debug","-IC:\\Qt\\6.6.3\\mingw_64\\mkspecs\\win32-g++","-isystem","C:\\Qt\\Tools\\mingw1120_64\\lib\\gcc\\x86_64-w64-mingw32\\11.2.0\\include\\c++","-isystem","C:\\Qt\\Tools\\mingw1120_64\\lib\\gcc\\x86_64-w64-mingw32\\11.2.0\\include\\c++\\x86_64-w64-mingw32","-isystem","C:\\Qt\\Tools\\mingw1120_64\\lib\\gcc\\x86_64-w64-mingw32\\11.2.0\\include\\c++\\backward","-isystem","C:\\Qt\\Tools\\QtCreator\\bin\\clang\\lib\\clang\\17\\include","-isystem","C:\\Qt\\Tools\\mingw1120_64\\x86_64-w64-mingw32\\include","-fmessage-length=0","-fdiagnostics-show-note-include-stack","-fretain-comments-from-system-headers","-fmacro-backtrace-limit=0","-ferror-limit=1000","-x","c++-header","D:\\Qt\\Project\\EntryPage\\arms.h"],"directory":"D:/Qt/Project/EntryPage/build/Desktop_Qt_6_6_3_MinGW_64_bit-Debug/.qtc_clangd","file":"D:/Qt/Project/EntryPage/arms.h"},{"arguments":["clang","-Wno-documentation-unknown-command","-Wno-unknown-warning-option","-Wno-unknown-pragmas","-nostdinc","-nostdinc++","-g","-Wall","-Wextra","-Wextra","-fexceptions","-mthreads","-fsyntax-only","-m64","--target=x86_64-w64-mingw32","-std=gnu++17","-DUNICODE","-D_UNICODE","-DWIN32","-DMINGW_HAS_SECURE_API","-DQT_QML_DEBUG","-DQT_WIDGETS_LIB","-DQT_MULTIMEDIA_LIB","-DQT_GUI_LIB","-DQT_NETWORK_LIB","-DQT_CORE_LIB","-DQT_NEEDS_QMAIN","-DQ_CREATOR_RUN","-DQT_ANNOTATE_FUNCTION(x)=__attribute__((annotate(#x)))","-IC:\\Qt\\Tools\\QtCreator\\share\\qtcreator\\cplusplus\\wrappedMingwHeaders","-IC:\\Qt\\Tools\\QtCreator\\share\\qtcreator\\cplusplus\\wrappedQtHeaders","-IC:\\Qt\\Tools\\QtCreator\\share\\qtcreator\\cplusplus\\wrappedQtHeaders\\QtCore","-ID:\\Qt\\Project\\EntryPage","-IC:\\Qt\\6.6.3\\mingw_64\\include","-IC:\\Qt\\6.6.3\\mingw_64\\include\\QtWidgets","-IC:\\Qt\\6.6.3\\mingw_64\\include\\QtMultimedia","-IC:\\Qt\\6.6.3\\mingw_64\\include\\QtGui","-IC:\\Qt\\6.6.3\\mingw_64\\include\\QtNetwork","-IC:\\Qt\\6.6.3\\mingw_64\\include\\QtCore","-ID:\\Qt\\Project\\EntryPage\\build\\Desktop_Qt_6_6_3_MinGW_64_bit-Debug\\debug","-ID:\\Qt\\Project\\EntryPage\\build\\Desktop_Qt_6_6_3_MinGW_64_bit-Debug","-IC:\\Qt\\6.6.3\\mingw_64\\mkspecs\\win32-g++","-isystem","C:\\Qt\\Tools\\mingw1120_64\\lib\\gcc\\x86_64-w64-mingw32\\11.2.0\\include\\c++","-isystem","C:\\Qt\\Tools\\mingw1120_64\\lib\\gcc\\x86_64-w64-mingw32\\11.2.0\\include\\c++\\x86_64-w64-mingw32","-isystem","C:\\Qt\\Tools\\mingw1120_64\\lib\\gcc\\x86_64-w64-mingw32\\11.2.0\\include\\c++\\backward","-isystem","C:\\Qt\\Tools\\QtCreator\\bin\\clang\\lib\\clang\\17\\include","-isystem","C:\\Qt\\Tools\\mingw1120_64\\x86_64-w64-mingw32\\include","-fmessage-length=0","-fdiagnostics-show-note-include-stack","-fretain-comments-from-system-headers","-fmacro-backtrace-limit=0","-ferror-limit=1000","-x","c++-header","D:\\Qt\\Project\\EntryPage\\dialoggameai.h"],"directory":"D:/Qt/Project/EntryPage/build/Desktop_Qt_6_6_3_MinGW_64_bit-Debug/.qtc_clangd","file":"D:/Qt/Project/EntryPage/dialoggameai.h"},{"arguments":["clang","-Wno-documentation-unknown-command","-Wno-unknown-warning-option","-Wno-unknown-pragmas","-nostdinc","-nostdinc++","-g","-Wall","-Wextra","-Wextra","-fexceptions","-mthreads","-fsyntax-only","-m64","--target=x86_64-w64-mingw32","-std=gnu++17","-DUNICODE","-D_UNICODE","-DWIN32","-DMINGW_HAS_SECURE_API","-DQT_QML_DEBUG","-DQT_WIDGETS_LIB","-DQT_MULTIMEDIA_LIB","-DQT_GUI_LIB","-DQT_NETWORK_LIB","-DQT_CORE_LIB","-DQT_NEEDS_QMAIN","-DQ_CREATOR_RUN","-DQT_ANNOTATE_FUNCTION(x)=__attribute__((annotate(#x)))","-IC:\\Qt\\Tools\\QtCreator\\share\\qtcreator\\cplusplus\\wrappedMingwHeaders","-IC:\\Qt\\Tools\\QtCreator\\share\\qtcreator\\cplusplus\\wrappedQtHeaders","-IC:\\Qt\\Tools\\QtCreator\\share\\qtcreator\\cplusplus\\wrappedQtHeaders\\QtCore","-ID:\\Qt\\Project\\EntryPage","-IC:\\Qt\\6.6.3\\mingw_64\\include","-IC:\\Qt\\6.6.3\\mingw_64\\include\\QtWidgets","-IC:\\Qt\\6.6.3\\mingw_64\\include\\QtMultimedia","-IC:\\Qt\\6.6.3\\mingw_64\\include\\QtGui","-IC:\\Qt\\6.6.3\\mingw_64\\include\\QtNetwork","-IC:\\Qt\\6.6.3\\mingw_64\\include\\QtCore","-ID:\\Qt\\Project\\EntryPage\\build\\Desktop_Qt_6_6_3_MinGW_64_bit-Debug\\debug","-ID:\\Qt\\Project\\EntryPage\\build\\Desktop_Qt_6_6_3_MinGW_64_bit-Debug","-IC:\\Qt\\6.6.3\\mingw_64\\mkspecs\\win32-g++","-isystem","C:\\Qt\\Tools\\mingw1120_64\\lib\\gcc\\x86_64-w64-mingw32\\11.2.0\\include\\c++","-isystem","C:\\Qt\\Tools\\mingw1120_64\\lib\\gcc\\x86_64-w64-mingw32\\11.2.0\\include\\c++\\x86_64-w64-mingw32","-isystem","C:\\Qt\\Tools\\mingw1120_64\\lib\\gcc\\x86_64-w64-mingw32\\11.2.0\\include\\c++\\backward","-isystem","C:\\Qt\\Tools\\QtCreator\\bin\\clang\\lib\\clang\\17\\include","-isystem","C:\\Qt\\Tools\\mingw1120_64\\x86_64-w64-mingw32\\include","-fmessage-length=0","-fdiagnostics-show-note-include-stack","-fretain-comments-from-system-headers","-fmacro-backtrace-limit=0","-ferror-limit=1000","-x","c++-header","D:\\Qt\\Project\\EntryPage\\dialoggetarm.h"],"directory":"D:/Qt/Project/EntryPage/build/Desktop_Qt_6_6_3_MinGW_64_bit-Debug/.qtc_clangd","file":"D:/Qt/Project/EntryPage/dialoggetarm.h"},{"arguments":["clang","-Wno-documentation-unknown-command","-Wno-unknown-warning-option","-Wno-unknown-pragmas","-nostdinc","-nostdinc++","-g","-Wall","-Wextra","-Wextra","-fexceptions","-mthreads","-fsyntax-only","-m64","--target=x86_64-w64-mingw32","-std=gnu++17","-DUNICODE","-D_UNICODE","-DWIN32","-DMINGW_HAS_SECURE_API","-DQT_QML_DEBUG","-DQT_WIDGETS_LIB","-DQT_MULTIMEDIA_LIB","-DQT_GUI_LIB","-DQT_NETWORK_LIB","-DQT_CORE_LIB","-DQT_NEEDS_QMAIN","-DQ_CREATOR_RUN","-DQT_ANNOTATE_FUNCTION(x)=__attribute__((annotate(#x)))","-IC:\\Qt\\Tools\\QtCreator\\share\\qtcreator\\cplusplus\\wrappedMingwHeaders","-IC:\\Qt\\Tools\\QtCreator\\share\\qtcreator\\cplusplus\\wrappedQtHeaders","-IC:\\Qt\\Tools\\QtCreator\\share\\qtcreator\\cplusplus\\wrappedQtHeaders\\QtCore","-ID:\\Qt\\Project\\EntryPage","-IC:\\Qt\\6.6.3\\mingw_64\\include","-IC:\\Qt\\6.6.3\\mingw_64\\include\\QtWidgets","-IC:\\Qt\\6.6.3\\mingw_64\\include\\QtMultimedia","-IC:\\Qt\\6.6.3\\mingw_64\\include\\QtGui","-IC:\\Qt\\6.6.3\\mingw_64\\include\\QtNetwork","-IC:\\Qt\\6.6.3\\mingw_64\\include\\QtCore","-ID:\\Qt\\Project\\EntryPage\\build\\Desktop_Qt_6_6_3_MinGW_64_bit-Debug\\debug","-ID:\\Qt\\Project\\EntryPage\\build\\Desktop_Qt_6_6_3_MinGW_64_bit-Debug","-IC:\\Qt\\6.6.3\\mingw_64\\mkspecs\\win32-g++","-isystem","C:\\Qt\\Tools\\mingw1120_64\\lib\\gcc\\x86_64-w64-mingw32\\11.2.0\\include\\c++","-isystem","C:\\Qt\\Tools\\mingw1120_64\\lib\\gcc\\x86_64-w64-mingw32\\11.2.0\\include\\c++\\x86_64-w64-mingw32","-isystem","C:\\Qt\\Tools\\mingw1120_64\\lib\\gcc\\x86_64-w64-mingw32\\11.2.0\\include\\c++\\backward","-isystem","C:\\Qt\\Tools\\QtCreator\\bin\\clang\\lib\\clang\\17\\include","-isystem","C:\\Qt\\Tools\\mingw1120_64\\x86_64-w64-mingw32\\include","-fmessage-length=0","-fdiagnostics-show-note-include-stack","-fretain-comments-from-system-headers","-fmacro-backtrace-limit=0","-ferror-limit=1000","-x","c++-header","D:\\Qt\\Project\\EntryPage\\dialogpage1.h"],"directory":"D:/Qt/Project/EntryPage/build/Desktop_Qt_6_6_3_MinGW_64_bit-Debug/.qtc_clangd","file":"D:/Qt/Project/EntryPage/dialogpage1.h"},{"arguments":["clang","-Wno-documentation-unknown-command","-Wno-unknown-warning-option","-Wno-unknown-pragmas","-nostdinc","-nostdinc++","-g","-Wall","-Wextra","-Wextra","-fexceptions","-mthreads","-fsyntax-only","-m64","--target=x86_64-w64-mingw32","-std=gnu++17","-DUNICODE","-D_UNICODE","-DWIN32","-DMINGW_HAS_SECURE_API","-DQT_QML_DEBUG","-DQT_WIDGETS_LIB","-DQT_MULTIMEDIA_LIB","-DQT_GUI_LIB","-DQT_NETWORK_LIB","-DQT_CORE_LIB","-DQT_NEEDS_QMAIN","-DQ_CREATOR_RUN","-DQT_ANNOTATE_FUNCTION(x)=__attribute__((annotate(#x)))","-IC:\\Qt\\Tools\\QtCreator\\share\\qtcreator\\cplusplus\\wrappedMingwHeaders","-IC:\\Qt\\Tools\\QtCreator\\share\\qtcreator\\cplusplus\\wrappedQtHeaders","-IC:\\Qt\\Tools\\QtCreator\\share\\qtcreator\\cplusplus\\wrappedQtHeaders\\QtCore","-ID:\\Qt\\Project\\EntryPage","-IC:\\Qt\\6.6.3\\mingw_64\\include","-IC:\\Qt\\6.6.3\\mingw_64\\include\\QtWidgets","-IC:\\Qt\\6.6.3\\mingw_64\\include\\QtMultimedia","-IC:\\Qt\\6.6.3\\mingw_64\\include\\QtGui","-IC:\\Qt\\6.6.3\\mingw_64\\include\\QtNetwork","-IC:\\Qt\\6.6.3\\mingw_64\\include\\QtCore","-ID:\\Qt\\Project\\EntryPage\\build\\Desktop_Qt_6_6_3_MinGW_64_bit-Debug\\debug","-ID:\\Qt\\Project\\EntryPage\\build\\Desktop_Qt_6_6_3_MinGW_64_bit-Debug","-IC:\\Qt\\6.6.3\\mingw_64\\mkspecs\\win32-g++","-isystem","C:\\Qt\\Tools\\mingw1120_64\\lib\\gcc\\x86_64-w64-mingw32\\11.2.0\\include\\c++","-isystem","C:\\Qt\\Tools\\mingw1120_64\\lib\\gcc\\x86_64-w64-mingw32\\11.2.0\\include\\c++\\x86_64-w64-mingw32","-isystem","C:\\Qt\\Tools\\mingw1120_64\\lib\\gcc\\x86_64-w64-mingw32\\11.2.0\\include\\c++\\backward","-isystem","C:\\Qt\\Tools\\QtCreator\\bin\\clang\\lib\\clang\\17\\include","-isystem","C:\\Qt\\Tools\\mingw1120_64\\x86_64-w64-mingw32\\include","-fmessage-length=0","-fdiagnostics-show-note-include-stack","-fretain-comments-from-system-headers","-fmacro-backtrace-limit=0","-ferror-limit=1000","-x","c++-header","D:\\Qt\\Project\\EntryPage\\dialogsetgameboard.h"],"directory":"D:/Qt/Project/EntryPage/build/Desktop_Qt_6_6_3_MinGW_64_bit-Debug/.qtc_clangd","file":"D:/Qt/Project/EntryPage/dialogsetgameboard.h"},{"arguments":["clang","-Wno-documentation-unknown-command","-Wno-unknown-warning-option","-Wno-unknown-pragmas","-nostdinc","-nostdinc++","-g","-Wall","-Wextra","-Wextra","-fexceptions","-mthreads","-fsyntax-only","-m64","--target=x86_64-w64-mingw32","-std=gnu++17","-DUNICODE","-D_UNICODE","-DWIN32","-DMINGW_HAS_SECURE_API","-DQT_QML_DEBUG","-DQT_WIDGETS_LIB","-DQT_MULTIMEDIA_LIB","-DQT_GUI_LIB","-DQT_NETWORK_LIB","-DQT_CORE_LIB","-DQT_NEEDS_QMAIN","-DQ_CREATOR_RUN","-DQT_ANNOTATE_FUNCTION(x)=__attribute__((annotate(#x)))","-IC:\\Qt\\Tools\\QtCreator\\share\\qtcreator\\cplusplus\\wrappedMingwHeaders","-IC:\\Qt\\Tools\\QtCreator\\share\\qtcreator\\cplusplus\\wrappedQtHeaders","-IC:\\Qt\\Tools\\QtCreator\\share\\qtcreator\\cplusplus\\wrappedQtHeaders\\QtCore","-ID:\\Qt\\Project\\EntryPage","-IC:\\Qt\\6.6.3\\mingw_64\\include","-IC:\\Qt\\6.6.3\\mingw_64\\include\\QtWidgets","-IC:\\Qt\\6.6.3\\mingw_64\\include\\QtMultimedia","-IC:\\Qt\\6.6.3\\mingw_64\\include\\QtGui","-IC:\\Qt\\6.6.3\\mingw_64\\include\\QtNetwork","-IC:\\Qt\\6.6.3\\mingw_64\\include\\QtCore","-ID:\\Qt\\Project\\EntryPage\\build\\Desktop_Qt_6_6_3_MinGW_64_bit-Debug\\debug","-ID:\\Qt\\Project\\EntryPage\\build\\Desktop_Qt_6_6_3_MinGW_64_bit-Debug","-IC:\\Qt\\6.6.3\\mingw_64\\mkspecs\\win32-g++","-isystem","C:\\Qt\\Tools\\mingw1120_64\\lib\\gcc\\x86_64-w64-mingw32\\11.2.0\\include\\c++","-isystem","C:\\Qt\\Tools\\mingw1120_64\\lib\\gcc\\x86_64-w64-mingw32\\11.2.0\\include\\c++\\x86_64-w64-mingw32","-isystem","C:\\Qt\\Tools\\mingw1120_64\\lib\\gcc\\x86_64-w64-mingw32\\11.2.0\\include\\c++\\backward","-isystem","C:\\Qt\\Tools\\QtCreator\\bin\\clang\\lib\\clang\\17\\include","-isystem","C:\\Qt\\Tools\\mingw1120_64\\x86_64-w64-mingw32\\include","-fmessage-length=0","-fdiagnostics-show-note-include-stack","-fretain-comments-from-system-headers","-fmacro-backtrace-limit=0","-ferror-limit=1000","-x","c++-header","D:\\Qt\\Project\\EntryPage\\draggablebutton.h"],"directory":"D:/Qt/Project/EntryPage/build/Desktop_Qt_6_6_3_MinGW_64_bit-Debug/.qtc_clangd","file":"D:/Qt/Project/EntryPage/draggablebutton.h"},{"arguments":["clang","-Wno-documentation-unknown-command","-Wno-unknown-warning-option","-Wno-unknown-pragmas","-nostdinc","-nostdinc++","-g","-Wall","-Wextra","-Wextra","-fexceptions","-mthreads","-fsyntax-only","-m64","--target=x86_64-w64-mingw32","-std=gnu++17","-DUNICODE","-D_UNICODE","-DWIN32","-DMINGW_HAS_SECURE_API","-DQT_QML_DEBUG","-DQT_WIDGETS_LIB","-DQT_MULTIMEDIA_LIB","-DQT_GUI_LIB","-DQT_NETWORK_LIB","-DQT_CORE_LIB","-DQT_NEEDS_QMAIN","-DQ_CREATOR_RUN","-DQT_ANNOTATE_FUNCTION(x)=__attribute__((annotate(#x)))","-IC:\\Qt\\Tools\\QtCreator\\share\\qtcreator\\cplusplus\\wrappedMingwHeaders","-IC:\\Qt\\Tools\\QtCreator\\share\\qtcreator\\cplusplus\\wrappedQtHeaders","-IC:\\Qt\\Tools\\QtCreator\\share\\qtcreator\\cplusplus\\wrappedQtHeaders\\QtCore","-ID:\\Qt\\Project\\EntryPage","-IC:\\Qt\\6.6.3\\mingw_64\\include","-IC:\\Qt\\6.6.3\\mingw_64\\include\\QtWidgets","-IC:\\Qt\\6.6.3\\mingw_64\\include\\QtMultimedia","-IC:\\Qt\\6.6.3\\mingw_64\\include\\QtGui","-IC:\\Qt\\6.6.3\\mingw_64\\include\\QtNetwork","-IC:\\Qt\\6.6.3\\mingw_64\\include\\QtCore","-ID:\\Qt\\Project\\EntryPage\\build\\Desktop_Qt_6_6_3_MinGW_64_bit-Debug\\debug","-ID:\\Qt\\Project\\EntryPage\\build\\Desktop_Qt_6_6_3_MinGW_64_bit-Debug","-IC:\\Qt\\6.6.3\\mingw_64\\mkspecs\\win32-g++","-isystem","C:\\Qt\\Tools\\mingw1120_64\\lib\\gcc\\x86_64-w64-mingw32\\11.2.0\\include\\c++","-isystem","C:\\Qt\\Tools\\mingw1120_64\\lib\\gcc\\x86_64-w64-mingw32\\11.2.0\\include\\c++\\x86_64-w64-mingw32","-isystem","C:\\Qt\\Tools\\mingw1120_64\\lib\\gcc\\x86_64-w64-mingw32\\11.2.0\\include\\c++\\backward","-isystem","C:\\Qt\\Tools\\QtCreator\\bin\\clang\\lib\\clang\\17\\include","-isystem","C:\\Qt\\Tools\\mingw1120_64\\x86_64-w64-mingw32\\include","-fmessage-length=0","-fdiagnostics-show-note-include-stack","-fretain-comments-from-system-headers","-fmacro-backtrace-limit=0","-ferror-limit=1000","-x","c++-header","D:\\Qt\\Project\\EntryPage\\gameboard.h"],"directory":"D:/Qt/Project/EntryPage/build/Desktop_Qt_6_6_3_MinGW_64_bit-Debug/.qtc_clangd","file":"D:/Qt/Project/EntryPage/gameboard.h"},{"arguments":["clang","-Wno-documentation-unknown-command","-Wno-unknown-warning-option","-Wno-unknown-pragmas","-nostdinc","-nostdinc++","-g","-Wall","-Wextra","-Wextra","-fexceptions","-mthreads","-fsyntax-only","-m64","--target=x86_64-w64-mingw32","-std=gnu++17","-DUNICODE","-D_UNICODE","-DWIN32","-DMINGW_HAS_SECURE_API","-DQT_QML_DEBUG","-DQT_WIDGETS_LIB","-DQT_MULTIMEDIA_LIB","-DQT_GUI_LIB","-DQT_NETWORK_LIB","-DQT_CORE_LIB","-DQT_NEEDS_QMAIN","-DQ_CREATOR_RUN","-DQT_ANNOTATE_FUNCTION(x)=__attribute__((annotate(#x)))","-IC:\\Qt\\Tools\\QtCreator\\share\\qtcreator\\cplusplus\\wrappedMingwHeaders","-IC:\\Qt\\Tools\\QtCreator\\share\\qtcreator\\cplusplus\\wrappedQtHeaders","-IC:\\Qt\\Tools\\QtCreator\\share\\qtcreator\\cplusplus\\wrappedQtHeaders\\QtCore","-ID:\\Qt\\Project\\EntryPage","-IC:\\Qt\\6.6.3\\mingw_64\\include","-IC:\\Qt\\6.6.3\\mingw_64\\include\\QtWidgets","-IC:\\Qt\\6.6.3\\mingw_64\\include\\QtMultimedia","-IC:\\Qt\\6.6.3\\mingw_64\\include\\QtGui","-IC:\\Qt\\6.6.3\\mingw_64\\include\\QtNetwork","-IC:\\Qt\\6.6.3\\mingw_64\\include\\QtCore","-ID:\\Qt\\Project\\EntryPage\\build\\Desktop_Qt_6_6_3_MinGW_64_bit-Debug\\debug","-ID:\\Qt\\Project\\EntryPage\\build\\Desktop_Qt_6_6_3_MinGW_64_bit-Debug","-IC:\\Qt\\6.6.3\\mingw_64\\mkspecs\\win32-g++","-isystem","C:\\Qt\\Tools\\mingw1120_64\\lib\\gcc\\x86_64-w64-mingw32\\11.2.0\\include\\c++","-isystem","C:\\Qt\\Tools\\mingw1120_64\\lib\\gcc\\x86_64-w64-mingw32\\11.2.0\\include\\c++\\x86_64-w64-mingw32","-isystem","C:\\Qt\\Tools\\mingw1120_64\\lib\\gcc\\x86_64-w64-mingw32\\11.2.0\\include\\c++\\backward","-isystem","C:\\Qt\\Tools\\QtCreator\\bin\\clang\\lib\\clang\\17\\include","-isystem","C:\\Qt\\Tools\\mingw1120_64\\x86_64-w64-mingw32\\include","-fmessage-length=0","-fdiagnostics-show-note-include-stack","-fretain-comments-from-system-headers","-fmacro-backtrace-limit=0","-ferror-limit=1000","-x","c++-header","D:\\Qt\\Project\\EntryPage\\hashpassword.h"],"directory":"D:/Qt/Project/EntryPage/build/Desktop_Qt_6_6_3_MinGW_64_bit-Debug/.qtc_clangd","file":"D:/Qt/Project/EntryPage/hashpassword.h"},{"arguments":["clang","-Wno-documentation-unknown-command","-Wno-unknown-warning-option","-Wno-unknown-pragmas","-nostdinc","-nostdinc++","-g","-Wall","-Wextra","-Wextra","-fexceptions","-mthreads","-fsyntax-only","-m64","--target=x86_64-w64-mingw32","-std=gnu++17","-DUNICODE","-D_UNICODE","-DWIN32","-DMINGW_HAS_SECURE_API","-DQT_QML_DEBUG","-DQT_WIDGETS_LIB","-DQT_MULTIMEDIA_LIB","-DQT_GUI_LIB","-DQT_NETWORK_LIB","-DQT_CORE_LIB","-DQT_NEEDS_QMAIN","-DQ_CREATOR_RUN","-DQT_ANNOTATE_FUNCTION(x)=__attribute__((annotate(#x)))","-IC:\\Qt\\Tools\\QtCreator\\share\\qtcreator\\cplusplus\\wrappedMingwHeaders","-IC:\\Qt\\Tools\\QtCreator\\share\\qtcreator\\cplusplus\\wrappedQtHeaders","-IC:\\Qt\\Tools\\QtCreator\\share\\qtcreator\\cplusplus\\wrappedQtHeaders\\QtCore","-ID:\\Qt\\Project\\EntryPage","-IC:\\Qt\\6.6.3\\mingw_64\\include","-IC:\\Qt\\6.6.3\\mingw_64\\include\\QtWidgets","-IC:\\Qt\\6.6.3\\mingw_64\\include\\QtMultimedia","-IC:\\Qt\\6.6.3\\mingw_64\\include\\QtGui","-IC:\\Qt\\6.6.3\\mingw_64\\include\\QtNetwork","-IC:\\Qt\\6.6.3\\mingw_64\\include\\QtCore","-ID:\\Qt\\Project\\EntryPage\\build\\Desktop_Qt_6_6_3_MinGW_64_bit-Debug\\debug","-ID:\\Qt\\Project\\EntryPage\\build\\Desktop_Qt_6_6_3_MinGW_64_bit-Debug","-IC:\\Qt\\6.6.3\\mingw_64\\mkspecs\\win32-g++","-isystem","C:\\Qt\\Tools\\mingw1120_64\\lib\\gcc\\x86_64-w64-mingw32\\11.2.0\\include\\c++","-isystem","C:\\Qt\\Tools\\mingw1120_64\\lib\\gcc\\x86_64-w64-mingw32\\11.2.0\\include\\c++\\x86_64-w64-mingw32","-isystem","C:\\Qt\\Tools\\mingw1120_64\\lib\\gcc\\x86_64-w64-mingw32\\11.2.0\\include\\c++\\backward","-isystem","C:\\Qt\\Tools\\QtCreator\\bin\\clang\\lib\\clang\\17\\include","-isystem","C:\\Qt\\Tools\\mingw1120_64\\x86_64-w64-mingw32\\include","-fmessage-length=0","-fdiagnostics-show-note-include-stack","-fretain-comments-from-system-headers","-fmacro-backtrace-limit=0","-ferror-limit=1000","-x","c++-header","D:\\Qt\\Project\\EntryPage\\mainwindow.h"],"directory":"D:/Qt/Project/EntryPage/build/Desktop_Qt_6_6_3_MinGW_64_bit-Debug/.qtc_clangd","file":"D:/Qt/Project/EntryPage/mainwindow.h"},{"arguments":["clang","-Wno-documentation-unknown-command","-Wno-unknown-warning-option","-Wno-unknown-pragmas","-nostdinc","-nostdinc++","-g","-Wall","-Wextra","-Wextra","-fexceptions","-mthreads","-fsyntax-only","-m64","--target=x86_64-w64-mingw32","-std=gnu++17","-DUNICODE","-D_UNICODE","-DWIN32","-DMINGW_HAS_SECURE_API","-DQT_QML_DEBUG","-DQT_WIDGETS_LIB","-DQT_MULTIMEDIA_LIB","-DQT_GUI_LIB","-DQT_NETWORK_LIB","-DQT_CORE_LIB","-DQT_NEEDS_QMAIN","-DQ_CREATOR_RUN","-DQT_ANNOTATE_FUNCTION(x)=__attribute__((annotate(#x)))","-IC:\\Qt\\Tools\\QtCreator\\share\\qtcreator\\cplusplus\\wrappedMingwHeaders","-IC:\\Qt\\Tools\\QtCreator\\share\\qtcreator\\cplusplus\\wrappedQtHeaders","-IC:\\Qt\\Tools\\QtCreator\\share\\qtcreator\\cplusplus\\wrappedQtHeaders\\QtCore","-ID:\\Qt\\Project\\EntryPage","-IC:\\Qt\\6.6.3\\mingw_64\\include","-IC:\\Qt\\6.6.3\\mingw_64\\include\\QtWidgets","-IC:\\Qt\\6.6.3\\mingw_64\\include\\QtMultimedia","-IC:\\Qt\\6.6.3\\mingw_64\\include\\QtGui","-IC:\\Qt\\6.6.3\\mingw_64\\include\\QtNetwork","-IC:\\Qt\\6.6.3\\mingw_64\\include\\QtCore","-ID:\\Qt\\Project\\EntryPage\\build\\Desktop_Qt_6_6_3_MinGW_64_bit-Debug\\debug","-ID:\\Qt\\Project\\EntryPage\\build\\Desktop_Qt_6_6_3_MinGW_64_bit-Debug","-IC:\\Qt\\6.6.3\\mingw_64\\mkspecs\\win32-g++","-isystem","C:\\Qt\\Tools\\mingw1120_64\\lib\\gcc\\x86_64-w64-mingw32\\11.2.0\\include\\c++","-isystem","C:\\Qt\\Tools\\mingw1120_64\\lib\\gcc\\x86_64-w64-mingw32\\11.2.0\\include\\c++\\x86_64-w64-mingw32","-isystem","C:\\Qt\\Tools\\mingw1120_64\\lib\\gcc\\x86_64-w64-mingw32\\11.2.0\\include\\c++\\backward","-isystem","C:\\Qt\\Tools\\QtCreator\\bin\\clang\\lib\\clang\\17\\include","-isystem","C:\\Qt\\Tools\\mingw1120_64\\x86_64-w64-mingw32\\include","-fmessage-length=0","-fdiagnostics-show-note-include-stack","-fretain-comments-from-system-headers","-fmacro-backtrace-limit=0","-ferror-limit=1000","-x","c++-header","D:\\Qt\\Project\\EntryPage\\dialogloginclicked.h"],"directory":"D:/Qt/Project/EntryPage/build/Desktop_Qt_6_6_3_MinGW_64_bit-Debug/.qtc_clangd","file":"D:/Qt/Project/EntryPage/dialogloginclicked.h"},{"arguments":["clang","-Wno-documentation-unknown-command","-Wno-unknown-warning-option","-Wno-unknown-pragmas","-nostdinc","-nostdinc++","-g","-Wall","-Wextra","-Wextra","-fexceptions","-mthreads","-fsyntax-only","-m64","--target=x86_64-w64-mingw32","-std=gnu++17","-DUNICODE","-D_UNICODE","-DWIN32","-DMINGW_HAS_SECURE_API","-DQT_QML_DEBUG","-DQT_WIDGETS_LIB","-DQT_MULTIMEDIA_LIB","-DQT_GUI_LIB","-DQT_NETWORK_LIB","-DQT_CORE_LIB","-DQT_NEEDS_QMAIN","-DQ_CREATOR_RUN","-DQT_ANNOTATE_FUNCTION(x)=__attribute__((annotate(#x)))","-IC:\\Qt\\Tools\\QtCreator\\share\\qtcreator\\cplusplus\\wrappedMingwHeaders","-IC:\\Qt\\Tools\\QtCreator\\share\\qtcreator\\cplusplus\\wrappedQtHeaders","-IC:\\Qt\\Tools\\QtCreator\\share\\qtcreator\\cplusplus\\wrappedQtHeaders\\QtCore","-ID:\\Qt\\Project\\EntryPage","-IC:\\Qt\\6.6.3\\mingw_64\\include","-IC:\\Qt\\6.6.3\\mingw_64\\include\\QtWidgets","-IC:\\Qt\\6.6.3\\mingw_64\\include\\QtMultimedia","-IC:\\Qt\\6.6.3\\mingw_64\\include\\QtGui","-IC:\\Qt\\6.6.3\\mingw_64\\include\\QtNetwork","-IC:\\Qt\\6.6.3\\mingw_64\\include\\QtCore","-ID:\\Qt\\Project\\EntryPage\\build\\Desktop_Qt_6_6_3_MinGW_64_bit-Debug\\debug","-ID:\\Qt\\Project\\EntryPage\\build\\Desktop_Qt_6_6_3_MinGW_64_bit-Debug","-IC:\\Qt\\6.6.3\\mingw_64\\mkspecs\\win32-g++","-isystem","C:\\Qt\\Tools\\mingw1120_64\\lib\\gcc\\x86_64-w64-mingw32\\11.2.0\\include\\c++","-isystem","C:\\Qt\\Tools\\mingw1120_64\\lib\\gcc\\x86_64-w64-mingw32\\11.2.0\\include\\c++\\x86_64-w64-mingw32","-isystem","C:\\Qt\\Tools\\mingw1120_64\\lib\\gcc\\x86_64-w64-mingw32\\11.2.0\\include\\c++\\backward","-isystem","C:\\Qt\\Tools\\QtCreator\\bin\\clang\\lib\\clang\\17\\include","-isystem","C:\\Qt\\Tools\\mingw1120_64\\x86_64-w64-mingw32\\include","-fmessage-length=0","-fdiagnostics-show-note-include-stack","-fretain-comments-from-system-headers","-fmacro-backtrace-limit=0","-ferror-limit=1000","-x","c++-header","D:\\Qt\\Project\\EntryPage\\dialogsignupclicked.h"],"directory":"D:/Qt/Project/EntryPage/build/Desktop_Qt_6_6_3_MinGW_64_bit-Debug/.qtc_clangd","file":"D:/Qt/Project/EntryPage/dialogsignupclicked.h"},{"arguments":["clang","-Wno-documentation-unknown-command","-Wno-unknown-warning-option","-Wno-unknown-pragmas","-nostdinc","-nostdinc++","-g","-Wall","-Wextra","-Wextra","-fexceptions","-mthreads","-fsyntax-only","-m64","--target=x86_64-w64-mingw32","-std=gnu++17","-DUNICODE","-D_UNICODE","-DWIN32","-DMINGW_HAS_SECURE_API","-DQT_QML_DEBUG","-DQT_WIDGETS_LIB","-DQT_MULTIMEDIA_LIB","-DQT_GUI_LIB","-DQT_NETWORK_LIB","-DQT_CORE_LIB","-DQT_NEEDS_QMAIN","-DQ_CREATOR_RUN","-DQT_ANNOTATE_FUNCTION(x)=__attribute__((annotate(#x)))","-IC:\\Qt\\Tools\\QtCreator\\share\\qtcreator\\cplusplus\\wrappedMingwHeaders","-IC:\\Qt\\Tools\\QtCreator\\share\\qtcreator\\cplusplus\\wrappedQtHeaders","-IC:\\Qt\\Tools\\QtCreator\\share\\qtcreator\\cplusplus\\wrappedQtHeaders\\QtCore","-ID:\\Qt\\Project\\EntryPage","-IC:\\Qt\\6.6.3\\mingw_64\\include","-IC:\\Qt\\6.6.3\\mingw_64\\include\\QtWidgets","-IC:\\Qt\\6.6.3\\mingw_64\\include\\QtMultimedia","-IC:\\Qt\\6.6.3\\mingw_64\\include\\QtGui","-IC:\\Qt\\6.6.3\\mingw_64\\include\\QtNetwork","-IC:\\Qt\\6.6.3\\mingw_64\\include\\QtCore","-ID:\\Qt\\Project\\EntryPage\\build\\Desktop_Qt_6_6_3_MinGW_64_bit-Debug\\debug","-ID:\\Qt\\Project\\EntryPage\\build\\Desktop_Qt_6_6_3_MinGW_64_bit-Debug","-IC:\\Qt\\6.6.3\\mingw_64\\mkspecs\\win32-g++","-isystem","C:\\Qt\\Tools\\mingw1120_64\\lib\\gcc\\x86_64-w64-mingw32\\11.2.0\\include\\c++","-isystem","C:\\Qt\\Tools\\mingw1120_64\\lib\\gcc\\x86_64-w64-mingw32\\11.2.0\\include\\c++\\x86_64-w64-mingw32","-isystem","C:\\Qt\\Tools\\mingw1120_64\\lib\\gcc\\x86_64-w64-mingw32\\11.2.0\\include\\c++\\backward","-isystem","C:\\Qt\\Tools\\QtCreator\\bin\\clang\\lib\\clang\\17\\include","-isystem","C:\\Qt\\Tools\\mingw1120_64\\x86_64-w64-mingw32\\include","-fmessage-length=0","-fdiagnostics-show-note-include-stack","-fretain-comments-from-system-headers","-fmacro-backtrace-limit=0","-ferror-limit=1000","-x","c++-header","D:\\Qt\\Project\\EntryPage\\musicplayer.h"],"directory":"D:/Qt/Project/EntryPage/build/Desktop_Qt_6_6_3_MinGW_64_bit-Debug/.qtc_clangd","file":"D:/Qt/Project/EntryPage/musicplayer.h"},{"arguments":["clang","-Wno-documentation-unknown-command","-Wno-unknown-warning-option","-Wno-unknown-pragmas","-nostdinc","-nostdinc++","-g","-Wall","-Wextra","-Wextra","-fexceptions","-mthreads","-fsyntax-only","-m64","--target=x86_64-w64-mingw32","-std=gnu++17","-DUNICODE","-D_UNICODE","-DWIN32","-DMINGW_HAS_SECURE_API","-DQT_QML_DEBUG","-DQT_WIDGETS_LIB","-DQT_MULTIMEDIA_LIB","-DQT_GUI_LIB","-DQT_NETWORK_LIB","-DQT_CORE_LIB","-DQT_NEEDS_QMAIN","-DQ_CREATOR_RUN","-DQT_ANNOTATE_FUNCTION(x)=__attribute__((annotate(#x)))","-IC:\\Qt\\Tools\\QtCreator\\share\\qtcreator\\cplusplus\\wrappedMingwHeaders","-IC:\\Qt\\Tools\\QtCreator\\share\\qtcreator\\cplusplus\\wrappedQtHeaders","-IC:\\Qt\\Tools\\QtCreator\\share\\qtcreator\\cplusplus\\wrappedQtHeaders\\QtCore","-ID:\\Qt\\Project\\EntryPage","-IC:\\Qt\\6.6.3\\mingw_64\\include","-IC:\\Qt\\6.6.3\\mingw_64\\include\\QtWidgets","-IC:\\Qt\\6.6.3\\mingw_64\\include\\QtMultimedia","-IC:\\Qt\\6.6.3\\mingw_64\\include\\QtGui","-IC:\\Qt\\6.6.3\\mingw_64\\include\\QtNetwork","-IC:\\Qt\\6.6.3\\mingw_64\\include\\QtCore","-ID:\\Qt\\Project\\EntryPage\\build\\Desktop_Qt_6_6_3_MinGW_64_bit-Debug\\debug","-ID:\\Qt\\Project\\EntryPage\\build\\Desktop_Qt_6_6_3_MinGW_64_bit-Debug","-IC:\\Qt\\6.6.3\\mingw_64\\mkspecs\\win32-g++","-isystem","C:\\Qt\\Tools\\mingw1120_64\\lib\\gcc\\x86_64-w64-mingw32\\11.2.0\\include\\c++","-isystem","C:\\Qt\\Tools\\mingw1120_64\\lib\\gcc\\x86_64-w64-mingw32\\11.2.0\\include\\c++\\x86_64-w64-mingw32","-isystem","C:\\Qt\\Tools\\mingw1120_64\\lib\\gcc\\x86_64-w64-mingw32\\11.2.0\\include\\c++\\backward","-isystem","C:\\Qt\\Tools\\QtCreator\\bin\\clang\\lib\\clang\\17\\include","-isystem","C:\\Qt\\Tools\\mingw1120_64\\x86_64-w64-mingw32\\include","-fmessage-length=0","-fdiagnostics-show-note-include-stack","-fretain-comments-from-system-headers","-fmacro-backtrace-limit=0","-ferror-limit=1000","-x","c++-header","D:\\Qt\\Project\\EntryPage\\ship.h"],"directory":"D:/Qt/Project/EntryPage/build/Desktop_Qt_6_6_3_MinGW_64_bit-Debug/.qtc_clangd","file":"D:/Qt/Project/EntryPage/ship.h"},{"arguments":["clang","-Wno-documentation-unknown-command","-Wno-unknown-warning-option","-Wno-unknown-pragmas","-nostdinc","-nostdinc++","-g","-Wall","-Wextra","-Wextra","-fexceptions","-mthreads","-fsyntax-only","-m64","--target=x86_64-w64-mingw32","-std=gnu++17","-DUNICODE","-D_UNICODE","-DWIN32","-DMINGW_HAS_SECURE_API","-DQT_QML_DEBUG","-DQT_WIDGETS_LIB","-DQT_MULTIMEDIA_LIB","-DQT_GUI_LIB","-DQT_NETWORK_LIB","-DQT_CORE_LIB","-DQT_NEEDS_QMAIN","-DQ_CREATOR_RUN","-DQT_ANNOTATE_FUNCTION(x)=__attribute__((annotate(#x)))","-IC:\\Qt\\Tools\\QtCreator\\share\\qtcreator\\cplusplus\\wrappedMingwHeaders","-IC:\\Qt\\Tools\\QtCreator\\share\\qtcreator\\cplusplus\\wrappedQtHeaders","-IC:\\Qt\\Tools\\QtCreator\\share\\qtcreator\\cplusplus\\wrappedQtHeaders\\QtCore","-ID:\\Qt\\Project\\EntryPage","-IC:\\Qt\\6.6.3\\mingw_64\\include","-IC:\\Qt\\6.6.3\\mingw_64\\include\\QtWidgets","-IC:\\Qt\\6.6.3\\mingw_64\\include\\QtMultimedia","-IC:\\Qt\\6.6.3\\mingw_64\\include\\QtGui","-IC:\\Qt\\6.6.3\\mingw_64\\include\\QtNetwork","-IC:\\Qt\\6.6.3\\mingw_64\\include\\QtCore","-ID:\\Qt\\Project\\EntryPage\\build\\Desktop_Qt_6_6_3_MinGW_64_bit-Debug\\debug","-ID:\\Qt\\Project\\EntryPage\\build\\Desktop_Qt_6_6_3_MinGW_64_bit-Debug","-IC:\\Qt\\6.6.3\\mingw_64\\mkspecs\\win32-g++","-isystem","C:\\Qt\\Tools\\mingw1120_64\\lib\\gcc\\x86_64-w64-mingw32\\11.2.0\\include\\c++","-isystem","C:\\Qt\\Tools\\mingw1120_64\\lib\\gcc\\x86_64-w64-mingw32\\11.2.0\\include\\c++\\x86_64-w64-mingw32","-isystem","C:\\Qt\\Tools\\mingw1120_64\\lib\\gcc\\x86_64-w64-mingw32\\11.2.0\\include\\c++\\backward","-isystem","C:\\Qt\\Tools\\QtCreator\\bin\\clang\\lib\\clang\\17\\include","-isystem","C:\\Qt\\Tools\\mingw1120_64\\x86_64-w64-mingw32\\include","-fmessage-length=0","-fdiagnostics-show-note-include-stack","-fretain-comments-from-system-headers","-fmacro-backtrace-limit=0","-ferror-limit=1000","-x","c++-header","D:\\Qt\\Project\\EntryPage\\user.h"],"directory":"D:/Qt/Project/EntryPage/build/Desktop_Qt_6_6_3_MinGW_64_bit-Debug/.qtc_clangd","file":"D:/Qt/Project/EntryPage/user.h"},{"arguments":["clang","-Wno-documentation-unknown-command","-Wno-unknown-warning-option","-Wno-unknown-pragmas","-nostdinc","-nostdinc++","-g","-Wall","-Wextra","-Wextra","-fexceptions","-mthreads","-fsyntax-only","-m64","--target=x86_64-w64-mingw32","-std=gnu++17","-DUNICODE","-D_UNICODE","-DWIN32","-DMINGW_HAS_SECURE_API","-DQT_QML_DEBUG","-DQT_WIDGETS_LIB","-DQT_MULTIMEDIA_LIB","-DQT_GUI_LIB","-DQT_NETWORK_LIB","-DQT_CORE_LIB","-DQT_NEEDS_QMAIN","-DQ_CREATOR_RUN","-DQT_ANNOTATE_FUNCTION(x)=__attribute__((annotate(#x)))","-IC:\\Qt\\Tools\\QtCreator\\share\\qtcreator\\cplusplus\\wrappedMingwHeaders","-IC:\\Qt\\Tools\\QtCreator\\share\\qtcreator\\cplusplus\\wrappedQtHeaders","-IC:\\Qt\\Tools\\QtCreator\\share\\qtcreator\\cplusplus\\wrappedQtHeaders\\QtCore","-ID:\\Qt\\Project\\EntryPage","-IC:\\Qt\\6.6.3\\mingw_64\\include","-IC:\\Qt\\6.6.3\\mingw_64\\include\\QtWidgets","-IC:\\Qt\\6.6.3\\mingw_64\\include\\QtMultimedia","-IC:\\Qt\\6.6.3\\mingw_64\\include\\QtGui","-IC:\\Qt\\6.6.3\\mingw_64\\include\\QtNetwork","-IC:\\Qt\\6.6.3\\mingw_64\\include\\QtCore","-ID:\\Qt\\Project\\EntryPage\\build\\Desktop_Qt_6_6_3_MinGW_64_bit-Debug\\debug","-ID:\\Qt\\Project\\EntryPage\\build\\Desktop_Qt_6_6_3_MinGW_64_bit-Debug","-IC:\\Qt\\6.6.3\\mingw_64\\mkspecs\\win32-g++","-isystem","C:\\Qt\\Tools\\mingw1120_64\\lib\\gcc\\x86_64-w64-mingw32\\11.2.0\\include\\c++","-isystem","C:\\Qt\\Tools\\mingw1120_64\\lib\\gcc\\x86_64-w64-mingw32\\11.2.0\\include\\c++\\x86_64-w64-mingw32","-isystem","C:\\Qt\\Tools\\mingw1120_64\\lib\\gcc\\x86_64-w64-mingw32\\11.2.0\\include\\c++\\backward","-isystem","C:\\Qt\\Tools\\QtCreator\\bin\\clang\\lib\\clang\\17\\include","-isystem","C:\\Qt\\Tools\\mingw1120_64\\x86_64-w64-mingw32\\include","-fmessage-length=0","-fdiagnostics-show-note-include-stack","-fretain-comments-from-system-headers","-fmacro-backtrace-limit=0","-ferror-limit=1000","-x","c++-header","D:\\Qt\\Project\\EntryPage\\validator.h"],"directory":"D:/Qt/Project/EntryPage/build/Desktop_Qt_6_6_3_MinGW_64_bit-Debug/.qtc_clangd","file":"D:/Qt/Project/EntryPage/validator.h"},{"arguments":["clang","-Wno-documentation-unknown-command","-Wno-unknown-warning-option","-Wno-unknown-pragmas","-nostdinc","-nostdinc++","-g","-Wall","-Wextra","-Wextra","-fexceptions","-mthreads","-fsyntax-only","-m64","--target=x86_64-w64-mingw32","-std=gnu++17","-DUNICODE","-D_UNICODE","-DWIN32","-DMINGW_HAS_SECURE_API","-DQT_QML_DEBUG","-DQT_WIDGETS_LIB","-DQT_MULTIMEDIA_LIB","-DQT_GUI_LIB","-DQT_NETWORK_LIB","-DQT_CORE_LIB","-DQT_NEEDS_QMAIN","-DQ_CREATOR_RUN","-DQT_ANNOTATE_FUNCTION(x)=__attribute__((annotate(#x)))","-IC:\\Qt\\Tools\\QtCreator\\share\\qtcreator\\cplusplus\\wrappedMingwHeaders","-IC:\\Qt\\Tools\\QtCreator\\share\\qtcreator\\cplusplus\\wrappedQtHeaders","-IC:\\Qt\\Tools\\QtCreator\\share\\qtcreator\\cplusplus\\wrappedQtHeaders\\QtCore","-ID:\\Qt\\Project\\EntryPage","-IC:\\Qt\\6.6.3\\mingw_64\\include","-IC:\\Qt\\6.6.3\\mingw_64\\include\\QtWidgets","-IC:\\Qt\\6.6.3\\mingw_64\\include\\QtMultimedia","-IC:\\Qt\\6.6.3\\mingw_64\\include\\QtGui","-IC:\\Qt\\6.6.3\\mingw_64\\include\\QtNetwork","-IC:\\Qt\\6.6.3\\mingw_64\\include\\QtCore","-ID:\\Qt\\Project\\EntryPage\\build\\Desktop_Qt_6_6_3_MinGW_64_bit-Debug\\debug","-ID:\\Qt\\Project\\EntryPage\\build\\Desktop_Qt_6_6_3_MinGW_64_bit-Debug","-IC:\\Qt\\6.6.3\\mingw_64\\mkspecs\\win32-g++","-isystem","C:\\Qt\\Tools\\mingw1120_64\\lib\\gcc\\x86_64-w64-mingw32\\11.2.0\\include\\c++","-isystem","C:\\Qt\\Tools\\mingw1120_64\\lib\\gcc\\x86_64-w64-mingw32\\11.2.0\\include\\c++\\x86_64-w64-mingw32","-isystem","C:\\Qt\\Tools\\mingw1120_64\\lib\\gcc\\x86_64-w64-mingw32\\11.2.0\\include\\c++\\backward","-isystem","C:\\Qt\\Tools\\QtCreator\\bin\\clang\\lib\\clang\\17\\include","-isystem","C:\\Qt\\Tools\\mingw1120_64\\x86_64-w64-mingw32\\include","-fmessage-length=0","-fdiagnostics-show-note-include-stack","-fretain-comments-from-system-headers","-fmacro-backtrace-limit=0","-ferror-limit=1000","-x","c++-header","D:\\Qt\\Project\\EntryPage\\build\\Desktop_Qt_6_6_3_MinGW_64_bit-Debug\\ui_dialogsignupclicked.h"],"directory":"D:/Qt/Project/EntryPage/build/Desktop_Qt_6_6_3_MinGW_64_bit-Debug/.qtc_clangd","file":"D:/Qt/Project/EntryPage/build/Desktop_Qt_6_6_3_MinGW_64_bit-Debug/ui_dialogsignupclicked.h"},{"arguments":["clang","-Wno-documentation-unknown-command","-Wno-unknown-warning-option","-Wno-unknown-pragmas","-nostdinc","-nostdinc++","-g","-Wall","-Wextra","-Wextra","-fexceptions","-mthreads","-fsyntax-only","-m64","--target=x86_64-w64-mingw32","-std=gnu++17","-DUNICODE","-D_UNICODE","-DWIN32","-DMINGW_HAS_SECURE_API","-DQT_QML_DEBUG","-DQT_WIDGETS_LIB","-DQT_MULTIMEDIA_LIB","-DQT_GUI_LIB","-DQT_NETWORK_LIB","-DQT_CORE_LIB","-DQT_NEEDS_QMAIN","-DQ_CREATOR_RUN","-DQT_ANNOTATE_FUNCTION(x)=__attribute__((annotate(#x)))","-IC:\\Qt\\Tools\\QtCreator\\share\\qtcreator\\cplusplus\\wrappedMingwHeaders","-IC:\\Qt\\Tools\\QtCreator\\share\\qtcreator\\cplusplus\\wrappedQtHeaders","-IC:\\Qt\\Tools\\QtCreator\\share\\qtcreator\\cplusplus\\wrappedQtHeaders\\QtCore","-ID:\\Qt\\Project\\EntryPage","-IC:\\Qt\\6.6.3\\mingw_64\\include","-IC:\\Qt\\6.6.3\\mingw_64\\include\\QtWidgets","-IC:\\Qt\\6.6.3\\mingw_64\\include\\QtMultimedia","-IC:\\Qt\\6.6.3\\mingw_64\\include\\QtGui","-IC:\\Qt\\6.6.3\\mingw_64\\include\\QtNetwork","-IC:\\Qt\\6.6.3\\mingw_64\\include\\QtCore","-ID:\\Qt\\Project\\EntryPage\\build\\Desktop_Qt_6_6_3_MinGW_64_bit-Debug\\debug","-ID:\\Qt\\Project\\EntryPage\\build\\Desktop_Qt_6_6_3_MinGW_64_bit-Debug","-IC:\\Qt\\6.6.3\\mingw_64\\mkspecs\\win32-g++","-isystem","C:\\Qt\\Tools\\mingw1120_64\\lib\\gcc\\x86_64-w64-mingw32\\11.2.0\\include\\c++","-isystem","C:\\Qt\\Tools\\mingw1120_64\\lib\\gcc\\x86_64-w64-mingw32\\11.2.0\\include\\c++\\x86_64-w64-mingw32","-isystem","C:\\Qt\\Tools\\mingw1120_64\\lib\\gcc\\x86_64-w64-mingw32\\11.2.0\\include\\c++\\backward","-isystem","C:\\Qt\\Tools\\QtCreator\\bin\\clang\\lib\\clang\\17\\include","-isystem","C:\\Qt\\Tools\\mingw1120_64\\x86_64-w64-mingw32\\include","-fmessage-length=0","-fdiagnostics-show-note-include-stack","-fretain-comments-from-system-headers","-fmacro-backtrace-limit=0","-ferror-limit=1000","-x","c++-header","D:\\Qt\\Project\\EntryPage\\build\\Desktop_Qt_6_6_3_MinGW_64_bit-Debug\\ui_dialogsetgameboard.h"],"directory":"D:/Qt/Project/EntryPage/build/Desktop_Qt_6_6_3_MinGW_64_bit-Debug/.qtc_clangd","file":"D:/Qt/Project/EntryPage/build/Desktop_Qt_6_6_3_MinGW_64_bit-Debug/ui_dialogsetgameboard.h"},{"arguments":["clang","-Wno-documentation-unknown-command","-Wno-unknown-warning-option","-Wno-unknown-pragmas","-nostdinc","-nostdinc++","-g","-Wall","-Wextra","-Wextra","-fexceptions","-mthreads","-fsyntax-only","-m64","--target=x86_64-w64-mingw32","-std=gnu++17","-DUNICODE","-D_UNICODE","-DWIN32","-DMINGW_HAS_SECURE_API","-DQT_QML_DEBUG","-DQT_WIDGETS_LIB","-DQT_MULTIMEDIA_LIB","-DQT_GUI_LIB","-DQT_NETWORK_LIB","-DQT_CORE_LIB","-DQT_NEEDS_QMAIN","-DQ_CREATOR_RUN","-DQT_ANNOTATE_FUNCTION(x)=__attribute__((annotate(#x)))","-IC:\\Qt\\Tools\\QtCreator\\share\\qtcreator\\cplusplus\\wrappedMingwHeaders","-IC:\\Qt\\Tools\\QtCreator\\share\\qtcreator\\cplusplus\\wrappedQtHeaders","-IC:\\Qt\\Tools\\QtCreator\\share\\qtcreator\\cplusplus\\wrappedQtHeaders\\QtCore","-ID:\\Qt\\Project\\EntryPage","-IC:\\Qt\\6.6.3\\mingw_64\\include","-IC:\\Qt\\6.6.3\\mingw_64\\include\\QtWidgets","-IC:\\Qt\\6.6.3\\mingw_64\\include\\QtMultimedia","-IC:\\Qt\\6.6.3\\mingw_64\\include\\QtGui","-IC:\\Qt\\6.6.3\\mingw_64\\include\\QtNetwork","-IC:\\Qt\\6.6.3\\mingw_64\\include\\QtCore","-ID:\\Qt\\Project\\EntryPage\\build\\Desktop_Qt_6_6_3_MinGW_64_bit-Debug\\debug","-ID:\\Qt\\Project\\EntryPage\\build\\Desktop_Qt_6_6_3_MinGW_64_bit-Debug","-IC:\\Qt\\6.6.3\\mingw_64\\mkspecs\\win32-g++","-isystem","C:\\Qt\\Tools\\mingw1120_64\\lib\\gcc\\x86_64-w64-mingw32\\11.2.0\\include\\c++","-isystem","C:\\Qt\\Tools\\mingw1120_64\\lib\\gcc\\x86_64-w64-mingw32\\11.2.0\\include\\c++\\x86_64-w64-mingw32","-isystem","C:\\Qt\\Tools\\mingw1120_64\\lib\\gcc\\x86_64-w64-mingw32\\11.2.0\\include\\c++\\backward","-isystem","C:\\Qt\\Tools\\QtCreator\\bin\\clang\\lib\\clang\\17\\include","-isystem","C:\\Qt\\Tools\\mingw1120_64\\x86_64-w64-mingw32\\include","-fmessage-length=0","-fdiagnostics-show-note-include-stack","-fretain-comments-from-system-headers","-fmacro-backtrace-limit=0","-ferror-limit=1000","-x","c++-header","D:\\Qt\\Project\\EntryPage\\build\\Desktop_Qt_6_6_3_MinGW_64_bit-Debug\\ui_dialogloginclicked.h"],"directory":"D:/Qt/Project/EntryPage/build/Desktop_Qt_6_6_3_MinGW_64_bit-Debug/.qtc_clangd","file":"D:/Qt/Project/EntryPage/build/Desktop_Qt_6_6_3_MinGW_64_bit-Debug/ui_dialogloginclicked.h"},{"arguments":["clang","-Wno-documentation-unknown-command","-Wno-unknown-warning-option","-Wno-unknown-pragmas","-nostdinc","-nostdinc++","-g","-Wall","-Wextra","-Wextra","-fexceptions","-mthreads","-fsyntax-only","-m64","--target=x86_64-w64-mingw32","-std=gnu++17","-DUNICODE","-D_UNICODE","-DWIN32","-DMINGW_HAS_SECURE_API","-DQT_QML_DEBUG","-DQT_WIDGETS_LIB","-DQT_MULTIMEDIA_LIB","-DQT_GUI_LIB","-DQT_NETWORK_LIB","-DQT_CORE_LIB","-DQT_NEEDS_QMAIN","-DQ_CREATOR_RUN","-DQT_ANNOTATE_FUNCTION(x)=__attribute__((annotate(#x)))","-IC:\\Qt\\Tools\\QtCreator\\share\\qtcreator\\cplusplus\\wrappedMingwHeaders","-IC:\\Qt\\Tools\\QtCreator\\share\\qtcreator\\cplusplus\\wrappedQtHeaders","-IC:\\Qt\\Tools\\QtCreator\\share\\qtcreator\\cplusplus\\wrappedQtHeaders\\QtCore","-ID:\\Qt\\Project\\EntryPage","-IC:\\Qt\\6.6.3\\mingw_64\\include","-IC:\\Qt\\6.6.3\\mingw_64\\include\\QtWidgets","-IC:\\Qt\\6.6.3\\mingw_64\\include\\QtMultimedia","-IC:\\Qt\\6.6.3\\mingw_64\\include\\QtGui","-IC:\\Qt\\6.6.3\\mingw_64\\include\\QtNetwork","-IC:\\Qt\\6.6.3\\mingw_64\\include\\QtCore","-ID:\\Qt\\Project\\EntryPage\\build\\Desktop_Qt_6_6_3_MinGW_64_bit-Debug\\debug","-ID:\\Qt\\Project\\EntryPage\\build\\Desktop_Qt_6_6_3_MinGW_64_bit-Debug","-IC:\\Qt\\6.6.3\\mingw_64\\mkspecs\\win32-g++","-isystem","C:\\Qt\\Tools\\mingw1120_64\\lib\\gcc\\x86_64-w64-mingw32\\11.2.0\\include\\c++","-isystem","C:\\Qt\\Tools\\mingw1120_64\\lib\\gcc\\x86_64-w64-mingw32\\11.2.0\\include\\c++\\x86_64-w64-mingw32","-isystem","C:\\Qt\\Tools\\mingw1120_64\\lib\\gcc\\x86_64-w64-mingw32\\11.2.0\\include\\c++\\backward","-isystem","C:\\Qt\\Tools\\QtCreator\\bin\\clang\\lib\\clang\\17\\include","-isystem","C:\\Qt\\Tools\\mingw1120_64\\x86_64-w64-mingw32\\include","-fmessage-length=0","-fdiagnostics-show-note-include-stack","-fretain-comments-from-system-headers","-fmacro-backtrace-limit=0","-ferror-limit=1000","-x","c++-header","D:\\Qt\\Project\\EntryPage\\build\\Desktop_Qt_6_6_3_MinGW_64_bit-Debug\\ui_mainwindow.h"],"directory":"D:/Qt/Project/EntryPage/build/Desktop_Qt_6_6_3_MinGW_64_bit-Debug/.qtc_clangd","file":"D:/Qt/Project/EntryPage/build/Desktop_Qt_6_6_3_MinGW_64_bit-Debug/ui_mainwindow.h"},{"arguments":["clang","-Wno-documentation-unknown-command","-Wno-unknown-warning-option","-Wno-unknown-pragmas","-nostdinc","-nostdinc++","-g","-Wall","-Wextra","-Wextra","-fexceptions","-mthreads","-fsyntax-only","-m64","--target=x86_64-w64-mingw32","-std=gnu++17","-DUNICODE","-D_UNICODE","-DWIN32","-DMINGW_HAS_SECURE_API","-DQT_QML_DEBUG","-DQT_WIDGETS_LIB","-DQT_MULTIMEDIA_LIB","-DQT_GUI_LIB","-DQT_NETWORK_LIB","-DQT_CORE_LIB","-DQT_NEEDS_QMAIN","-DQ_CREATOR_RUN","-DQT_ANNOTATE_FUNCTION(x)=__attribute__((annotate(#x)))","-IC:\\Qt\\Tools\\QtCreator\\share\\qtcreator\\cplusplus\\wrappedMingwHeaders","-IC:\\Qt\\Tools\\QtCreator\\share\\qtcreator\\cplusplus\\wrappedQtHeaders","-IC:\\Qt\\Tools\\QtCreator\\share\\qtcreator\\cplusplus\\wrappedQtHeaders\\QtCore","-ID:\\Qt\\Project\\EntryPage","-IC:\\Qt\\6.6.3\\mingw_64\\include","-IC:\\Qt\\6.6.3\\mingw_64\\include\\QtWidgets","-IC:\\Qt\\6.6.3\\mingw_64\\include\\QtMultimedia","-IC:\\Qt\\6.6.3\\mingw_64\\include\\QtGui","-IC:\\Qt\\6.6.3\\mingw_64\\include\\QtNetwork","-IC:\\Qt\\6.6.3\\mingw_64\\include\\QtCore","-ID:\\Qt\\Project\\EntryPage\\build\\Desktop_Qt_6_6_3_MinGW_64_bit-Debug\\debug","-ID:\\Qt\\Project\\EntryPage\\build\\Desktop_Qt_6_6_3_MinGW_64_bit-Debug","-IC:\\Qt\\6.6.3\\mingw_64\\mkspecs\\win32-g++","-isystem","C:\\Qt\\Tools\\mingw1120_64\\lib\\gcc\\x86_64-w64-mingw32\\11.2.0\\include\\c++","-isystem","C:\\Qt\\Tools\\mingw1120_64\\lib\\gcc\\x86_64-w64-mingw32\\11.2.0\\include\\c++\\x86_64-w64-mingw32","-isystem","C:\\Qt\\Tools\\mingw1120_64\\lib\\gcc\\x86_64-w64-mingw32\\11.2.0\\include\\c++\\backward","-isystem","C:\\Qt\\Tools\\QtCreator\\bin\\clang\\lib\\clang\\17\\include","-isystem","C:\\Qt\\Tools\\mingw1120_64\\x86_64-w64-mingw32\\include","-fmessage-length=0","-fdiagnostics-show-note-include-stack","-fretain-comments-from-system-headers","-fmacro-backtrace-limit=0","-ferror-limit=1000","-x","c++-header","D:\\Qt\\Project\\EntryPage\\build\\Desktop_Qt_6_6_3_MinGW_64_bit-Debug\\ui_dialoggetarm.h"],"directory":"D:/Qt/Project/EntryPage/build/Desktop_Qt_6_6_3_MinGW_64_bit-Debug/.qtc_clangd","file":"D:/Qt/Project/EntryPage/build/Desktop_Qt_6_6_3_MinGW_64_bit-Debug/ui_dialoggetarm.h"},{"arguments":["clang","-Wno-documentation-unknown-command","-Wno-unknown-warning-option","-Wno-unknown-pragmas","-nostdinc","-nostdinc++","-g","-Wall","-Wextra","-Wextra","-fexceptions","-mthreads","-fsyntax-only","-m64","--target=x86_64-w64-mingw32","-std=gnu++17","-DUNICODE","-D_UNICODE","-DWIN32","-DMINGW_HAS_SECURE_API","-DQT_QML_DEBUG","-DQT_WIDGETS_LIB","-DQT_MULTIMEDIA_LIB","-DQT_GUI_LIB","-DQT_NETWORK_LIB","-DQT_CORE_LIB","-DQT_NEEDS_QMAIN","-DQ_CREATOR_RUN","-DQT_ANNOTATE_FUNCTION(x)=__attribute__((annotate(#x)))","-IC:\\Qt\\Tools\\QtCreator\\share\\qtcreator\\cplusplus\\wrappedMingwHeaders","-IC:\\Qt\\Tools\\QtCreator\\share\\qtcreator\\cplusplus\\wrappedQtHeaders","-IC:\\Qt\\Tools\\QtCreator\\share\\qtcreator\\cplusplus\\wrappedQtHeaders\\QtCore","-ID:\\Qt\\Project\\EntryPage","-IC:\\Qt\\6.6.3\\mingw_64\\include","-IC:\\Qt\\6.6.3\\mingw_64\\include\\QtWidgets","-IC:\\Qt\\6.6.3\\mingw_64\\include\\QtMultimedia","-IC:\\Qt\\6.6.3\\mingw_64\\include\\QtGui","-IC:\\Qt\\6.6.3\\mingw_64\\include\\QtNetwork","-IC:\\Qt\\6.6.3\\mingw_64\\include\\QtCore","-ID:\\Qt\\Project\\EntryPage\\build\\Desktop_Qt_6_6_3_MinGW_64_bit-Debug\\debug","-ID:\\Qt\\Project\\EntryPage\\build\\Desktop_Qt_6_6_3_MinGW_64_bit-Debug","-IC:\\Qt\\6.6.3\\mingw_64\\mkspecs\\win32-g++","-isystem","C:\\Qt\\Tools\\mingw1120_64\\lib\\gcc\\x86_64-w64-mingw32\\11.2.0\\include\\c++","-isystem","C:\\Qt\\Tools\\mingw1120_64\\lib\\gcc\\x86_64-w64-mingw32\\11.2.0\\include\\c++\\x86_64-w64-mingw32","-isystem","C:\\Qt\\Tools\\mingw1120_64\\lib\\gcc\\x86_64-w64-mingw32\\11.2.0\\include\\c++\\backward","-isystem","C:\\Qt\\Tools\\QtCreator\\bin\\clang\\lib\\clang\\17\\include","-isystem","C:\\Qt\\Tools\\mingw1120_64\\x86_64-w64-mingw32\\include","-fmessage-length=0","-fdiagnostics-show-note-include-stack","-fretain-comments-from-system-headers","-fmacro-backtrace-limit=0","-ferror-limit=1000","-x","c++-header","D:\\Qt\\Project\\EntryPage\\build\\Desktop_Qt_6_6_3_MinGW_64_bit-Debug\\ui_dialoggameai.h"],"directory":"D:/Qt/Project/EntryPage/build/Desktop_Qt_6_6_3_MinGW_64_bit-Debug/.qtc_clangd","file":"D:/Qt/Project/EntryPage/build/Desktop_Qt_6_6_3_MinGW_64_bit-Debug/ui_dialoggameai.h"},{"arguments":["clang","-Wno-documentation-unknown-command","-Wno-unknown-warning-option","-Wno-unknown-pragmas","-nostdinc","-nostdinc++","-g","-Wall","-Wextra","-Wextra","-fexceptions","-mthreads","-fsyntax-only","-m64","--target=x86_64-w64-mingw32","-std=gnu++17","-DUNICODE","-D_UNICODE","-DWIN32","-DMINGW_HAS_SECURE_API","-DQT_QML_DEBUG","-DQT_WIDGETS_LIB","-DQT_MULTIMEDIA_LIB","-DQT_GUI_LIB","-DQT_NETWORK_LIB","-DQT_CORE_LIB","-DQT_NEEDS_QMAIN","-DQ_CREATOR_RUN","-DQT_ANNOTATE_FUNCTION(x)=__attribute__((annotate(#x)))","-IC:\\Qt\\Tools\\QtCreator\\share\\qtcreator\\cplusplus\\wrappedMingwHeaders","-IC:\\Qt\\Tools\\QtCreator\\share\\qtcreator\\cplusplus\\wrappedQtHeaders","-IC:\\Qt\\Tools\\QtCreator\\share\\qtcreator\\cplusplus\\wrappedQtHeaders\\QtCore","-ID:\\Qt\\Project\\EntryPage","-IC:\\Qt\\6.6.3\\mingw_64\\include","-IC:\\Qt\\6.6.3\\mingw_64\\include\\QtWidgets","-IC:\\Qt\\6.6.3\\mingw_64\\include\\QtMultimedia","-IC:\\Qt\\6.6.3\\mingw_64\\include\\QtGui","-IC:\\Qt\\6.6.3\\mingw_64\\include\\QtNetwork","-IC:\\Qt\\6.6.3\\mingw_64\\include\\QtCore","-ID:\\Qt\\Project\\EntryPage\\build\\Desktop_Qt_6_6_3_MinGW_64_bit-Debug\\debug","-ID:\\Qt\\Project\\EntryPage\\build\\Desktop_Qt_6_6_3_MinGW_64_bit-Debug","-IC:\\Qt\\6.6.3\\mingw_64\\mkspecs\\win32-g++","-isystem","C:\\Qt\\Tools\\mingw1120_64\\lib\\gcc\\x86_64-w64-mingw32\\11.2.0\\include\\c++","-isystem","C:\\Qt\\Tools\\mingw1120_64\\lib\\gcc\\x86_64-w64-mingw32\\11.2.0\\include\\c++\\x86_64-w64-mingw32","-isystem","C:\\Qt\\Tools\\mingw1120_64\\lib\\gcc\\x86_64-w64-mingw32\\11.2.0\\include\\c++\\backward","-isystem","C:\\Qt\\Tools\\QtCreator\\bin\\clang\\lib\\clang\\17\\include","-isystem","C:\\Qt\\Tools\\mingw1120_64\\x86_64-w64-mingw32\\include","-fmessage-length=0","-fdiagnostics-show-note-include-stack","-fretain-comments-from-system-headers","-fmacro-backtrace-limit=0","-ferror-limit=1000","-x","c++-header","D:\\Qt\\Project\\EntryPage\\build\\Desktop_Qt_6_6_3_MinGW_64_bit-Debug\\ui_dialogpage1.h"],"directory":"D:/Qt/Project/EntryPage/build/Desktop_Qt_6_6_3_MinGW_64_bit-Debug/.qtc_clangd","file":"D:/Qt/Project/EntryPage/build/Desktop_Qt_6_6_3_MinGW_64_bit-Debug/ui_dialogpage1.h"}]